{"skeleton":{"hash":"KOwqv8HL8QU","spine":"4.1.19","x":-72.09,"y":-8.91,"width":176.93,"height":350.17,"fps":60,"images":"./images/","audio":"F:/Kiai/Spine/Thief/B3Lance"},"bones":[{"name":"root","scaleX":-1},{"name":"Body","parent":"root","length":27.48,"rotation":99.62,"x":0.78,"y":109.18},{"name":"Body3","parent":"Body","length":46.45,"rotation":-12.01,"x":27.48},{"name":"Body2","parent":"Body3","length":38.2,"rotation":-4.62,"x":46.45},{"name":"Head","parent":"Body2","length":65.22,"rotation":-10.5,"x":37.79,"y":-0.96},{"name":"Ears","parent":"Head","length":22.55,"rotation":4.31,"x":74.86,"y":-11.2},{"name":"Ears2","parent":"Head","length":22.06,"rotation":-1.58,"x":74.18,"y":14.64},{"name":"Eye","parent":"Head","x":53.33,"y":-3.38},{"name":"Eye2","parent":"Head","x":51.59,"y":21.85},{"name":"Nose","parent":"Head","x":24.7,"y":13.51},{"name":"LArm","parent":"Body2","length":74.41,"rotation":-164.71,"x":31.44,"y":-41.37},{"name":"LArm2","parent":"LArm","length":43.14,"rotation":-20.43,"x":74.41},{"name":"RArm","parent":"Body2","length":67.05,"rotation":163.62,"x":33.01,"y":24.18},{"name":"RArm2","parent":"RArm","length":47.65,"rotation":-42.91,"x":72.05},{"name":"RLeg","parent":"Body","length":67.06,"rotation":169.2,"x":-4.34,"y":-14.64},{"name":"RLeg2","parent":"RLeg","length":38.62,"rotation":3.9,"x":67.06},{"name":"LLeg","parent":"Body","length":67.52,"rotation":169.21,"x":-0.72,"y":12.23},{"name":"LLeg2","parent":"LLeg","length":36.75,"rotation":2.6,"x":67.52},{"name":"Tail","parent":"Body","length":34.91,"rotation":-129.2,"x":0.85,"y":-19.71},{"name":"Tail2","parent":"Tail","length":32.62,"rotation":-29.47,"x":34.91},{"name":"Tail3","parent":"Tail2","length":35.36,"rotation":-31.94,"x":32.62},{"name":"Tail4","parent":"Tail3","length":37.67,"rotation":-1.4,"x":35.36,"y":0.46},{"name":"Lance","parent":"RArm2","rotation":-114.36,"x":48.9,"y":14.8},{"name":"Skirt2","parent":"Body3","rotation":17.25,"x":-44.05,"y":18.25},{"name":"Skirt","parent":"Body3","rotation":7.36,"x":-38.53,"y":-36.68},{"name":"RIK","parent":"root","x":16.4,"y":1.72,"color":"ff3f00ff"},{"name":"LIK","parent":"root","x":-11.62,"y":2.18,"color":"ff3f00ff"},{"name":"Beard","parent":"Head","x":6.82,"y":12.79},{"name":"band","parent":"Head","x":68.14,"y":-17.76},{"name":"RArm3","parent":"RArm","x":-2.17,"y":-5.58},{"name":"Body4","parent":"Body2","x":33.93,"y":-46.68},{"name":"Head2","parent":"Head","rotation":-2.91,"x":79.76,"y":-4.72,"scaleX":1.0932,"scaleY":1.0932},{"name":"Head3","parent":"Head2","rotation":-12.67,"x":-21.71,"y":-26.75},{"name":"Head4","parent":"Head2","x":-23.32,"y":27.57}],"slots":[{"name":"Samurai/ArmorArm2","bone":"RArm3","attachment":"ArmorArm"},{"name":"Ear2","bone":"Ears2","color":"858585ff","attachment":"Ear"},{"name":"Tail","bone":"root","attachment":"Tail"},{"name":"Braccio","bone":"root","attachment":"Braccio"},{"name":"Mano","bone":"root","attachment":"Mano"},{"name":"Lance","bone":"Lance","attachment":"Lance"},{"name":"Gamba","bone":"root","attachment":"Gamba"},{"name":"Piede","bone":"root","attachment":"Piede"},{"name":"Samurai/ArmorGamba","bone":"Skirt2","attachment":"ArmorGamba"},{"name":"Gamba2","bone":"root","attachment":"Gamba"},{"name":"Piede2","bone":"root","attachment":"Piede"},{"name":"Skirt","bone":"root","attachment":"Skirt"},{"name":"Samurai/ArmorGamba2","bone":"Skirt","attachment":"ArmorGamba"},{"name":"Body","bone":"root","attachment":"Body"},{"name":"Samurai/Helm2","bone":"Head4","color":"858585ff","attachment":"Helm1"},{"name":"Testa","bone":"root","attachment":"Testa"},{"name":"Ear","bone":"Ears","attachment":"Ear"},{"name":"Nose","bone":"Nose","attachment":"Nose"},{"name":"Eye","bone":"Eye","attachment":"Eye"},{"name":"Eye2","bone":"Eye2","attachment":"Eye"},{"name":"Beard","bone":"Beard","attachment":"Beard"},{"name":"Braccio2","bone":"root","attachment":"Braccio"},{"name":"Samurai/ArmorArm","bone":"Body4","attachment":"ArmorArm"},{"name":"Mano2","bone":"root","attachment":"Mano"},{"name":"T3/Band2","bone":"band","attachment":"Band"},{"name":"Samurai/Helm","bone":"Head2","attachment":"Samurai/Helm2"},{"name":"Samurai/Helm1","bone":"Head3","attachment":"Helm1"}],"ik":[{"name":"LIK","order":1,"bones":["LLeg","LLeg2"],"target":"LIK"},{"name":"RIK","bones":["RLeg","RLeg2"],"target":"RIK"}],"skins":[{"name":"Demon/Demon1","attachments":{"Body":{"Body":{"name":"Demon/Body","type":"linkedmesh","skin":"Thief/Thief1","parent":"Body","width":91,"height":127}},"Braccio":{"Braccio":{"name":"Samurai/Braccio","type":"linkedmesh","path":"T1/Braccio","color":"ffed16ff","skin":"Thief/Thief1","parent":"Braccio","width":27,"height":91}},"Braccio2":{"Braccio":{"name":"Samurai/Braccio","type":"linkedmesh","path":"T1/Braccio","color":"ffed16ff","skin":"Thief/Thief1","parent":"Braccio","width":27,"height":91}},"Ear":{"Ear":{"name":"Demon/Horn1","x":22.81,"y":-2.69,"scaleX":-1,"rotation":-93.5,"width":35,"height":56}},"Ear2":{"Ear":{"name":"Demon/Horn1","x":19.95,"y":0.77,"rotation":-87.61,"width":35,"height":56}},"Eye":{"Eye":{"name":"Demon/Eye","color":"ff0000ff","x":-2.08,"y":1.77,"rotation":-89.19,"width":23,"height":17}},"Eye2":{"Eye":{"name":"Demon/Eye","color":"ff0000ff","x":-1.12,"y":-1.23,"scaleX":-1,"rotation":-89.19,"width":23,"height":17}},"Gamba":{"Gamba":{"name":"T3/Gamba","type":"linkedmesh","color":"ff0000ff","skin":"Thief/Thief1","parent":"Gamba","width":21,"height":55}},"Gamba2":{"Gamba":{"name":"Samurai/Gamba","type":"linkedmesh","path":"T3/Gamba","color":"ff0000ff","skin":"Thief/Thief1","parent":"Gamba","width":21,"height":55}},"Lance":{"Lance":{"x":47.11,"y":0.23,"rotation":-88.89,"width":23,"height":350}},"Mano":{"Mano":{"name":"Samurai/Mano","type":"linkedmesh","path":"T3/Mano","skin":"Thief/Thief1","parent":"Mano","width":24,"height":45}},"Mano2":{"Mano":{"name":"Samurai/Mano","type":"linkedmesh","path":"T3/Mano","skin":"Thief/Thief1","parent":"Mano","width":24,"height":45}},"Piede":{"Piede":{"name":"Samurai/Piede","type":"linkedmesh","path":"T3/Piede","color":"858585ff","skin":"Thief/Thief1","parent":"Piede","width":22,"height":31}},"Piede2":{"Piede":{"name":"T3/Piede","type":"linkedmesh","skin":"Thief/Thief1","parent":"Piede","width":22,"height":31}},"Samurai/ArmorArm":{"ArmorArm":{"name":"Demon/ArmorArm","color":"ff0000ff","x":-6.18,"y":-4.21,"width":47,"height":61}},"Samurai/ArmorArm2":{"ArmorArm":{"name":"Demon/ArmorArm","color":"ff0000ff","x":12.88,"y":-3.68,"scaleY":-1,"rotation":-163.62,"width":47,"height":61}},"Skirt":{"Skirt":{"name":"T3/Skirt","type":"linkedmesh","color":"ff0000ff","skin":"Thief/Thief1","parent":"Skirt","width":68,"height":38}},"T3/Band2":{"Band":{"name":"T3/Band","x":0.69,"y":1.14,"scaleX":1.1139,"scaleY":1.1139,"rotation":-65.2,"width":75,"height":74}},"Testa":{"Testa":{"name":"Demon/Head","type":"linkedmesh","skin":"Thief/Thief1","parent":"Testa","width":79,"height":82}}}},{"name":"Demon/Demon2","attachments":{"Body":{"Body":{"name":"Demon/Body","type":"linkedmesh","color":"00ff0aff","skin":"Thief/Thief1","parent":"Body","width":91,"height":127}},"Braccio":{"Braccio":{"name":"Samurai/Braccio","type":"linkedmesh","path":"T1/Braccio","color":"00ff0aff","skin":"Thief/Thief1","parent":"Braccio","width":27,"height":91}},"Braccio2":{"Braccio":{"name":"Samurai/Braccio","type":"linkedmesh","path":"T1/Braccio","color":"00ff0aff","skin":"Thief/Thief1","parent":"Braccio","width":27,"height":91}},"Ear":{"Ear":{"name":"Demon/Horn1","x":22.81,"y":-2.69,"scaleX":-1,"rotation":-93.5,"width":35,"height":56}},"Ear2":{"Ear":{"name":"Demon/Horn1","x":19.95,"y":0.77,"rotation":-87.61,"width":35,"height":56}},"Eye":{"Eye":{"name":"Demon/Eye","color":"ff0000ff","x":-2.08,"y":1.77,"rotation":-89.19,"width":23,"height":17}},"Eye2":{"Eye":{"name":"Demon/Eye","color":"ff0000ff","x":-1.12,"y":-1.23,"scaleX":-1,"rotation":-89.19,"width":23,"height":17}},"Gamba":{"Gamba":{"name":"T3/Gamba","type":"linkedmesh","color":"89293cff","skin":"Thief/Thief1","parent":"Gamba","width":21,"height":55}},"Gamba2":{"Gamba":{"name":"Samurai/Gamba","type":"linkedmesh","path":"T3/Gamba","color":"89293cff","skin":"Thief/Thief1","parent":"Gamba","width":21,"height":55}},"Lance":{"Lance":{"x":47.11,"y":0.23,"rotation":-88.89,"width":23,"height":350}},"Mano":{"Mano":{"name":"Samurai/Mano","type":"linkedmesh","path":"T3/Mano","color":"00ff0aff","skin":"Thief/Thief1","parent":"Mano","width":24,"height":45}},"Mano2":{"Mano":{"name":"Samurai/Mano","type":"linkedmesh","path":"T3/Mano","color":"00ff0aff","skin":"Thief/Thief1","parent":"Mano","width":24,"height":45}},"Piede":{"Piede":{"name":"Samurai/Piede","type":"linkedmesh","path":"T3/Piede","color":"858585ff","skin":"Thief/Thief1","parent":"Piede","width":22,"height":31}},"Piede2":{"Piede":{"name":"T3/Piede","type":"linkedmesh","skin":"Thief/Thief1","parent":"Piede","width":22,"height":31}},"Skirt":{"Skirt":{"name":"T3/Skirt","type":"linkedmesh","color":"89293cff","skin":"Thief/Thief1","parent":"Skirt","width":68,"height":38}},"Testa":{"Testa":{"name":"Demon/Head","type":"linkedmesh","color":"00ff0aff","skin":"Thief/Thief1","parent":"Testa","width":79,"height":82}}}},{"name":"Samurai/Samurai","attachments":{"Beard":{"Beard":{"name":"Samurai/Mustache","rotation":-88.72,"width":42,"height":26}},"Body":{"Body":{"name":"Samurai/Body","type":"linkedmesh","skin":"Thief/Thief1","parent":"Body","width":91,"height":127}},"Braccio":{"Braccio":{"name":"Samurai/Braccio","type":"linkedmesh","skin":"Thief/Thief1","parent":"Braccio","width":27,"height":91}},"Braccio2":{"Braccio":{"name":"Samurai/Braccio","type":"linkedmesh","skin":"Thief/Thief1","parent":"Braccio","width":27,"height":91}},"Eye":{"Eye":{"x":-2.08,"y":1.77,"rotation":-89.19,"width":20,"height":17}},"Eye2":{"Eye":{"x":-1.12,"y":-1.23,"scaleX":-1,"rotation":-89.19,"width":20,"height":17}},"Gamba":{"Gamba":{"name":"Samurai/Gamba","type":"linkedmesh","color":"858585ff","skin":"Thief/Thief1","parent":"Gamba","width":24,"height":90}},"Gamba2":{"Gamba":{"name":"Samurai/Gamba","type":"linkedmesh","skin":"Thief/Thief1","parent":"Gamba","width":24,"height":90}},"Lance":{"Lance":{"x":47.11,"y":0.23,"rotation":-88.89,"width":23,"height":350}},"Mano":{"Mano":{"name":"Samurai/Mano","type":"linkedmesh","skin":"Thief/Thief1","parent":"Mano","width":26,"height":55}},"Mano2":{"Mano":{"name":"Samurai/Mano","type":"linkedmesh","skin":"Thief/Thief1","parent":"Mano","width":26,"height":55}},"Nose":{"Nose":{"name":"T2/Nose","x":-2.08,"y":-0.45,"rotation":-89.19,"width":15,"height":12}},"Piede":{"Piede":{"name":"Samurai/Piede","type":"linkedmesh","color":"858585ff","skin":"Thief/Thief1","parent":"Piede","width":25,"height":51}},"Piede2":{"Piede":{"name":"Samurai/Piede","type":"linkedmesh","skin":"Thief/Thief1","parent":"Piede","width":25,"height":51}},"Samurai/ArmorArm":{"ArmorArm":{"name":"Samurai/ArmorArm","x":-15.35,"y":79.9,"rotation":-82.98,"width":47,"height":61}},"Samurai/ArmorArm2":{"ArmorArm":{"name":"Samurai/ArmorArm","x":-0.19,"y":84.16,"scaleX":-1.0428,"scaleY":1.0428,"rotation":97.21,"width":47,"height":61}},"Samurai/ArmorGamba":{"ArmorGamba":{"name":"Samurai/ArmorGamba","x":3.5,"y":5.18,"rotation":-99.62,"width":40,"height":62}},"Samurai/ArmorGamba2":{"ArmorGamba":{"name":"Samurai/ArmorGamba","x":0.57,"y":-1.29,"scaleX":-1.197,"scaleY":1.197,"rotation":-99.62,"width":40,"height":62}},"Samurai/Helm":{"Samurai/Helm2":{"name":"Samurai/Helm","type":"mesh","uvs":[1,0.54717,1,1,0.49514,1,0,1,0,0.54042,0,0,0.45237,0,1,0,0.47595,0.55139],"triangles":[4,5,6,8,6,7,8,4,6,7,0,8,3,4,8,2,8,0,3,8,2,2,0,1],"vertices":[1.82,-31.08,-25.06,-26,-26.81,13.46,-23.23,34.15,3.46,27.8,34.91,28.18,35,5.44,33.55,-31.81,1.62,7.46],"hull":8,"edges":[10,12,12,14,2,4,4,6,2,0,0,14,4,16,16,12,0,16,6,8,8,10,16,8],"width":60,"height":58}},"Samurai/Helm1":{"Helm1":{"name":"Samurai/Helm1","x":-11.52,"y":-10.28,"scaleX":-1.4583,"scaleY":1.4583,"rotation":-72.49,"width":26,"height":49}},"Samurai/Helm2":{"Helm1":{"name":"Samurai/Helm1","x":-17.62,"y":3.02,"scaleX":1.2288,"scaleY":1.2288,"rotation":-87.38,"width":26,"height":49}},"Skirt":{"Skirt":{"name":"Samurai/Skirt","type":"linkedmesh","skin":"Thief/Thief1","parent":"Skirt","width":84,"height":58}},"Testa":{"Testa":{"name":"Samurai/Head","type":"linkedmesh","skin":"Thief/Thief1","parent":"Testa","width":79,"height":82}}}},{"name":"Thief/Thief1","attachments":{"Body":{"Body":{"name":"T1/Body","type":"mesh","uvs":[1,0.26092,1,0.67446,1,1,0.5378,1,0,1,0,0.71536,0,0.26092,0,0,0.37925,0,1,0,0.49419,0.7249,0.42674,0.2995],"triangles":[5,6,11,11,0,1,6,8,11,0,11,9,11,8,9,6,7,8,2,10,1,4,5,10,1,10,11,10,5,11,4,10,3,2,3,10],"vertices":[2,2,56.76,-59.02,0.39641,3,15.03,-58,0.60359,3,1,20.5,-43.68,0.27319,2,-8.63,-46.64,0.71537,3,-51.14,-50.93,0.01144,2,1,-7.77,-34.36,0.93918,2,-36.98,-31.46,0.06082,2,1,-0.75,7.11,0.99995,2,-26.59,9.29,5.0E-5,2,1,3.41,36.13,0.78789,2,-14.42,37.07,0.21211,3,1,41.19,42.75,0.4097,2,20.07,40.96,0.55538,3,-29.59,38.7,0.03493,3,1,99.98,39.68,0.00271,2,76.46,33.51,0.14326,3,27.22,35.82,0.85403,2,2,108.57,25.32,3.4E-4,3,59.88,30.25,0.99966,2,2,98.88,-15.99,1.3E-4,3,53.55,-11.71,0.99987,2,2,85.73,-63.63,0.14515,3,44.29,-60.26,0.85485,2,1,34.36,5.18,0.08673,2,8.25,4.5,0.91327,3,1,89.61,-5.5,1.0E-5,2,64.66,-10.25,8.9E-4,3,18.98,-8.75,0.9991],"hull":10,"edges":[14,16,16,18,4,6,6,8,4,2,6,20,2,20,8,10,20,10,10,12,12,14,16,22,22,20,12,22,2,0,0,18,22,0],"width":91,"height":127}},"Braccio":{"Braccio":{"name":"T1/Braccio","type":"mesh","uvs":[1,0.23041,1,0.42068,1,0.59192,1,0.77585,1,0.87732,1,1,0,1,0,0.89001,0,0.75682,0,0.59192,0,0.38263,0,0.17967,0,0,1,0],"triangles":[11,12,13,11,13,0,10,11,0,10,0,1,9,10,1,2,9,1,8,9,2,8,2,3,7,8,3,4,7,3,5,6,7,5,7,4],"vertices":[1,12,11.16,16.11,1,1,12,28.97,16.72,1,1,12,44.99,17.27,1,1,12,62.2,17.86,1,1,12,71.7,18.18,1,1,12,83.18,18.57,1,1,12,89.48,-15.55,1,1,12,79.19,-15.9,1,1,12,66.73,-16.33,1,1,12,51.29,-16.86,1,1,12,31.71,-17.53,1,1,12,12.72,-18.18,1,1,12,-4.1,-18.76,1,1,12,-10.4,15.37,1],"hull":14,"edges":[10,12,24,26,0,26,22,24,0,22,0,2,20,22,2,20,2,4,18,20,4,18,4,6,16,18,6,16,6,8,8,10,12,14,14,16,8,14],"width":27,"height":91}},"Braccio2":{"Braccio":{"name":"T1/Braccio","type":"mesh","uvs":[1,0.23041,1,0.42068,1,0.59192,1,0.77585,1,0.87732,1,1,0,1,0,0.89001,0,0.75682,0,0.59192,0,0.38263,0,0.17967,0,0,1,0],"triangles":[11,12,13,11,13,0,10,11,0,10,0,1,9,10,1,2,9,1,8,9,2,8,2,3,7,8,3,4,7,3,5,6,7,5,7,4],"vertices":[1,10,16.98,-15.76,1,1,10,34.06,-19.21,1,1,10,49.44,-22.32,1,1,10,65.95,-25.66,1,1,10,75.06,-27.5,1,1,10,86.07,-29.73,1,1,10,90.68,9.78,1,1,10,80.81,11.78,1,1,10,68.85,14.19,1,1,10,54.05,17.19,1,1,10,35.26,20.99,1,1,10,17.04,24.67,1,1,10,0.91,27.93,1,1,10,-3.7,-11.58,1],"hull":14,"edges":[10,12,24,26,0,26,22,24,0,22,0,2,20,22,2,20,2,4,18,20,4,18,4,6,16,18,6,16,6,8,8,10,12,14,14,16,8,14],"width":27,"height":91}},"Ear":{"Ear":{"name":"T1/Ear","x":22.72,"y":-2.34,"rotation":-93.5,"width":28,"height":58}},"Ear2":{"Ear":{"path":"T1/Ear","x":19.95,"y":0.77,"scaleX":-1,"rotation":-87.61,"width":28,"height":58}},"Eye":{"Eye":{"x":-2.08,"y":1.77,"rotation":-89.19,"width":20,"height":17}},"Eye2":{"Eye":{"x":-1.12,"y":-1.23,"scaleX":-1,"rotation":-89.19,"width":20,"height":17}},"Gamba":{"Gamba":{"name":"Samurai/Gamba","type":"mesh","path":"T1/Gamba","color":"858585ff","uvs":[1,0.26377,1,0.49463,1,0.6806,1,0.82809,1,1,0,1,0,0.88581,0,0.68701,0,0.48181,0,0.25736,0,0,1,0],"triangles":[9,10,11,9,11,0,8,9,0,8,0,1,7,8,1,2,7,1,7,2,3,6,7,3,4,5,6,4,6,3],"vertices":[1,16,11.66,20.33,1,1,16,32.44,20.76,1,1,16,49.17,21.1,1,1,16,62.44,21.37,1,1,16,77.91,21.69,1,1,16,78.69,-16.48,1,1,16,68.41,-16.69,1,1,16,50.53,-17.05,1,1,16,32.06,-17.43,1,1,16,11.86,-17.84,1,1,16,-11.29,-18.32,1,1,16,-12.07,19.85,1],"hull":12,"edges":[8,10,20,22,0,22,18,20,0,18,0,2,16,18,2,16,2,4,14,16,4,14,4,6,6,8,10,12,12,14,6,12],"width":24,"height":90}},"Gamba2":{"Gamba":{"name":"Samurai/Gamba","type":"mesh","path":"T1/Gamba","uvs":[1,0.26377,1,0.49463,1,0.6806,1,0.82809,1,1,0,1,0,0.88581,0,0.68701,0,0.48181,0,0.25736,0,0,1,0],"triangles":[9,10,11,9,11,0,8,9,0,8,0,1,7,8,1,2,7,1,7,2,3,6,7,3,4,5,6,4,6,3],"vertices":[1,14,12.55,21.7,1,1,14,33.32,22.13,1,1,14,50.06,22.47,1,1,14,63.33,22.75,1,1,14,78.8,23.06,1,1,14,79.64,-17.74,1,1,14,69.36,-17.95,1,1,14,51.47,-18.32,1,1,14,33.01,-18.7,1,1,14,12.81,-19.11,1,1,14,-10.35,-19.59,1,1,14,-11.18,21.22,1],"hull":12,"edges":[8,10,20,22,0,22,18,20,0,18,0,2,16,18,2,16,2,4,14,16,4,14,4,6,6,8,10,12,12,14,6,12],"width":24,"height":90}},"Lance":{"Lance":{"x":47.11,"y":0.23,"rotation":-88.89,"width":23,"height":350}},"Mano":{"Mano":{"name":"Samurai/Mano","type":"mesh","path":"T1/Mano","uvs":[1,0.22799,1,0.5428,1,0.77365,1,1,0,1,0,0.74217,0,0.40638,0,0.17552,0,0,1,0],"triangles":[7,8,9,7,9,0,6,7,0,6,0,1,5,6,1,5,1,2,4,5,2,4,2,3],"vertices":[1,13,9.11,9.15,1,1,13,26.13,12.32,1,1,13,38.61,14.65,1,1,13,50.85,16.93,1,1,13,55.61,-8.63,1,1,13,41.67,-11.23,1,1,13,23.52,-14.61,1,1,13,11.03,-16.94,1,1,13,1.54,-18.71,1,1,13,-3.22,6.85,1],"hull":10,"edges":[6,8,16,18,0,18,14,16,0,14,12,14,0,2,12,2,2,4,4,6,8,10,10,12,4,10],"width":26,"height":55}},"Mano2":{"Mano":{"name":"Samurai/Mano","type":"mesh","path":"T1/Mano","uvs":[1,0.22799,1,0.5428,1,0.77365,1,1,0,1,0,0.74217,0,0.40638,0,0.17552,0,0,1,0],"triangles":[7,8,9,7,9,0,6,7,0,6,0,1,5,6,1,5,1,2,4,5,2,4,2,3],"vertices":[1,11,8.83,-9.61,1,1,11,25.78,-13.11,1,1,11,38.22,-15.68,1,1,11,50.41,-18.2,1,1,11,55.67,7.27,1,1,11,41.78,10.14,1,1,11,23.7,13.87,1,1,11,11.26,16.44,1,1,11,1.81,18.39,1,1,11,-3.45,-7.07,1],"hull":10,"edges":[6,8,16,18,0,18,14,16,0,14,12,14,0,2,12,2,2,4,4,6,8,10,10,12,4,10],"width":26,"height":55}},"Nose":{"Nose":{"path":"T1/Nose","x":-2.08,"y":-0.45,"rotation":-89.19,"width":16,"height":20}},"Piede":{"Piede":{"name":"Samurai/Piede","type":"mesh","path":"T1/Piede","color":"858585ff","uvs":[1,0.24481,1,0.53904,1,0.78801,1,1,0,1,0,0.78801,0,0.55036,0,0.25613,0,0,1,0],"triangles":[8,9,0,7,8,0,7,0,1,6,7,1,2,5,6,2,6,1,4,5,2,4,2,3],"vertices":[1,17,3.83,15.82,1,1,17,18.83,15.44,1,1,17,31.53,15.13,1,1,17,42.33,14.86,1,1,17,41.71,-10.14,1,1,17,30.9,-9.87,1,1,17,18.78,-9.56,1,1,17,3.78,-9.19,1,1,17,-9.27,-8.86,1,1,17,-8.65,16.13,1],"hull":10,"edges":[6,8,16,18,0,18,14,16,0,14,0,2,12,14,2,12,2,4,4,6,8,10,10,12,4,10],"width":25,"height":51}},"Piede2":{"Piede":{"name":"Samurai/Piede","type":"mesh","path":"T1/Piede","uvs":[1,0.24481,1,0.53904,1,0.78801,1,1,0,1,0,0.78801,0,0.55036,0,0.25613,0,0,1,0],"triangles":[8,9,0,7,8,0,7,0,1,6,7,1,2,5,6,2,6,1,4,5,2,4,2,3],"vertices":[1,15,5.98,16.77,1,1,15,20.97,16.05,1,1,15,33.65,15.45,1,1,15,44.45,14.93,1,1,15,43.26,-10.04,1,1,15,32.46,-9.52,1,1,15,20.36,-8.95,1,1,15,5.37,-8.23,1,1,15,-7.68,-7.61,1,1,15,-6.49,17.36,1],"hull":10,"edges":[6,8,16,18,0,18,14,16,0,14,0,2,12,14,2,12,2,4,4,6,8,10,10,12,4,10],"width":25,"height":51}},"Skirt":{"Skirt":{"name":"Samurai/Skirt","type":"mesh","path":"T1/Skirt","uvs":[1,1,0.74581,1,0.45285,1,0.23313,1,0,1,0,0,0.17116,0,0.41905,0,0.77961,0,1,0],"triangles":[3,7,2,4,6,3,4,5,6,8,1,7,1,2,7,3,6,7,1,8,0,8,9,0],"vertices":[2,24,-22.8,-9.99,0.9996,23,-28.84,-64.86,4.0E-4,3,24,-19.23,11.06,0.83458,1,-37.07,-16.79,0.09716,23,-25.27,-43.81,0.06826,3,24,-15.12,35.32,0.25317,1,-32.96,7.47,0.26435,23,-21.16,-19.55,0.48248,3,24,-12.03,53.52,0.03583,1,-29.87,25.67,0.04545,23,-18.07,-1.35,0.91873,1,23,-14.8,17.95,1,2,1,30.59,35.28,0.59181,23,42.39,8.26,0.40819,2,1,28.18,21.11,0.71058,23,39.98,-5.91,0.28942,2,1,24.7,0.58,0.99625,23,36.5,-26.44,0.00375,2,24,37.48,-1.43,0.44907,1,19.64,-29.29,0.55093,2,24,34.39,-19.68,0.64136,1,16.55,-47.54,0.35864],"hull":10,"edges":[8,10,0,18,14,4,14,16,16,18,0,2,2,4,16,2,10,12,12,14,4,6,6,8,12,6],"width":84,"height":58}},"Tail":{"Tail":{"name":"Samurai/Tail","type":"mesh","path":"T1/Tail","uvs":[1,0.11619,1,0.26031,1,0.40824,1,0.5378,1,0.66738,1,0.80422,1,0.90802,1,1,0,1,0,0.91463,0,0.80362,0,0.67776,0,0.53355,0,0.40402,0,0.25236,0,0.13383,0,0,1,0],"triangles":[5,10,11,10,5,6,9,10,6,7,8,9,7,9,6,12,2,3,12,3,4,11,12,4,5,11,4,13,14,1,13,1,2,12,13,2,16,17,0,15,16,0,1,14,15,1,15,0],"vertices":[2,21,22.47,-8.17,0.99734,20,57.63,-8.26,0.00266,2,21,0,-8.86,0.01122,20,35.15,-8.4,0.98878,2,20,12.07,-8.55,0.99907,19,44.44,-8.89,9.3E-4,2,20,-8.14,-8.68,0.01668,19,24.24,-8.45,0.98332,2,19,4.03,-8.01,0.85739,18,39.05,-7.95,0.14261,1,18,17.71,-7.8,1,1,18,1.51,-7.69,1,1,18,-12.83,-7.6,1,1,18,-12.73,8.4,1,1,18,0.59,8.31,1,1,18,17.91,8.2,1,2,19,2.76,8.02,0.77487,18,37.54,8.06,0.22513,2,20,-7.58,7.32,0.02881,19,25.25,7.53,0.97119,1,20,12.62,7.45,1,2,21,0.75,7.17,0.93552,20,36.28,7.61,0.06448,1,21,19.23,7.74,1,1,21,40.1,8.38,1,1,21,40.59,-7.61,1],"hull":18,"edges":[14,16,32,34,30,32,0,34,30,0,28,30,0,2,28,2,26,28,2,4,26,4,24,26,4,6,24,6,22,24,6,8,22,8,20,22,8,10,20,10,16,18,18,20,10,12,12,14,18,12],"width":16,"height":156}},"Testa":{"Testa":{"name":"Samurai/Testa","type":"mesh","path":"T1/Testa","uvs":[1,0.29666,1,1,0,1,0,0.47835,0,0,0.29869,0,1,0,0.30628,0.59592],"triangles":[5,6,0,3,4,5,7,3,5,0,7,5,2,3,7,7,0,1,2,7,1],"vertices":[1,4,68.75,-40.37,1,1,4,-7.2,-41.44,1,1,4,-8.27,34.55,1,1,4,48.06,35.34,1,1,4,99.72,36.07,1,1,4,100.04,13.37,1,1,4,100.79,-39.92,1,1,4,35.69,11.89,1],"hull":7,"edges":[2,4,8,10,10,12,10,14,14,2,14,4,2,0,0,12,14,0,4,6,6,8,14,6],"width":76,"height":108}}}},{"name":"Thief/Thief2","attachments":{"Body":{"Body":{"name":"T2/Body","type":"linkedmesh","skin":"Thief/Thief1","parent":"Body","width":90,"height":108}},"Braccio":{"Braccio":{"name":"T2/Braccio","type":"linkedmesh","skin":"Thief/Thief1","parent":"Braccio","width":43,"height":61}},"Braccio2":{"Braccio":{"name":"T2/Braccio","type":"linkedmesh","skin":"Thief/Thief1","parent":"Braccio","width":43,"height":61}},"Eye":{"Eye":{"x":-2.08,"y":1.77,"rotation":-89.19,"width":20,"height":17}},"Eye2":{"Eye":{"x":-1.12,"y":-1.23,"scaleX":-1,"rotation":-89.19,"width":20,"height":17}},"Gamba":{"Gamba":{"name":"T3/Gamba","type":"linkedmesh","color":"858585ff","skin":"Thief/Thief1","parent":"Gamba","width":21,"height":55}},"Gamba2":{"Gamba":{"name":"T3/Gamba","type":"linkedmesh","skin":"Thief/Thief1","parent":"Gamba","width":21,"height":55}},"Lance":{"Lance":{"x":47.11,"y":0.23,"rotation":-88.89,"width":23,"height":350}},"Mano":{"Mano":{"name":"Samurai/Mano","type":"linkedmesh","path":"T2/Mano","skin":"Thief/Thief1","parent":"Mano","width":33,"height":52}},"Mano2":{"Mano":{"name":"Samurai/Mano","type":"linkedmesh","path":"T1/Mano","skin":"Thief/Thief1","parent":"Mano","width":26,"height":55}},"Nose":{"Nose":{"name":"T2/Nose","x":-2.08,"y":-0.45,"rotation":-89.19,"width":15,"height":12}},"Piede":{"Piede":{"name":"T3/Piede","type":"linkedmesh","color":"858585ff","skin":"Thief/Thief1","parent":"Piede","width":22,"height":31}},"Piede2":{"Piede":{"name":"T3/Piede","type":"linkedmesh","skin":"Thief/Thief1","parent":"Piede","width":22,"height":31}},"Skirt":{"Skirt":{"name":"T2/Skirt","type":"linkedmesh","skin":"Thief/Thief1","parent":"Skirt","width":112,"height":65}},"Testa":{"Testa":{"name":"Samurai/T2/Head2","type":"linkedmesh","path":"T2/Head","skin":"Thief/Thief1","parent":"Testa","width":87,"height":90}}}},{"name":"Thief/Thief3","attachments":{"Beard":{"Beard":{"name":"T3/Mustache","x":-1.94,"y":0.02,"rotation":-90.36,"width":43,"height":38}},"Body":{"Body":{"name":"T3/Body","type":"linkedmesh","skin":"Thief/Thief1","parent":"Body","width":60,"height":92}},"Braccio":{"Braccio":{"name":"Samurai/Braccio","type":"linkedmesh","path":"T1/Braccio","skin":"Thief/Thief1","parent":"Braccio","width":27,"height":91}},"Braccio2":{"Braccio":{"name":"Samurai/Braccio","type":"linkedmesh","path":"T1/Braccio","skin":"Thief/Thief1","parent":"Braccio","width":27,"height":91}},"Ear":{"Ear":{"path":"T3/Ear","x":22.72,"y":-2.34,"rotation":-93.5,"width":19,"height":41}},"Ear2":{"Ear":{"path":"T3/Ear","x":19.95,"y":0.77,"scaleX":-1,"rotation":-87.61,"width":19,"height":41}},"Eye":{"Eye":{"x":-2.08,"y":1.77,"rotation":-89.19,"width":20,"height":17}},"Eye2":{"Eye":{"x":-1.12,"y":-1.23,"scaleX":-1,"rotation":-89.19,"width":20,"height":17}},"Gamba":{"Gamba":{"name":"T3/Gamba","type":"linkedmesh","color":"858585ff","skin":"Thief/Thief1","parent":"Gamba","width":21,"height":55}},"Gamba2":{"Gamba":{"name":"Samurai/Gamba","type":"linkedmesh","path":"T3/Gamba","skin":"Thief/Thief1","parent":"Gamba","width":21,"height":55}},"Lance":{"Lance":{"x":47.11,"y":0.23,"rotation":-88.89,"width":23,"height":350}},"Mano":{"Mano":{"name":"Samurai/Mano","type":"linkedmesh","path":"T3/Mano","skin":"Thief/Thief1","parent":"Mano","width":24,"height":45}},"Mano2":{"Mano":{"name":"Samurai/Mano","type":"linkedmesh","path":"T3/Mano","skin":"Thief/Thief1","parent":"Mano","width":24,"height":45}},"Nose":{"Nose":{"name":"T3/Nose","x":-2.08,"y":-0.45,"rotation":-89.19,"width":17,"height":14}},"Piede":{"Piede":{"name":"Samurai/Piede","type":"linkedmesh","path":"T3/Piede","color":"858585ff","skin":"Thief/Thief1","parent":"Piede","width":22,"height":31}},"Piede2":{"Piede":{"name":"T3/Piede","type":"linkedmesh","skin":"Thief/Thief1","parent":"Piede","width":22,"height":31}},"Skirt":{"Skirt":{"name":"T3/Skirt","type":"linkedmesh","skin":"Thief/Thief1","parent":"Skirt","width":68,"height":38}},"T3/Band2":{"Band":{"name":"T3/Band","x":0.69,"y":1.14,"rotation":-65.2,"width":75,"height":74}},"Testa":{"Testa":{"name":"T3/Head","type":"linkedmesh","skin":"Thief/Thief1","parent":"Testa","width":61,"height":83}}}}],"events":{"activeAtkBaloon":{},"destroyEnemyGameObject":{},"endAttackPhase":{},"instantiateAtk":{}},"animations":{"die1":{"slots":{"Beard":{"rgba":[{"time":1,"color":"ffffffff"},{"time":2,"color":"ffffff00"}]},"Body":{"rgba":[{"time":1,"color":"ffffffff"},{"time":2,"color":"ffffff00"}]},"Braccio":{"rgba":[{"time":0.1667,"color":"858585ff","curve":"stepped"},{"time":1,"color":"858585ff"},{"time":2,"color":"85858500"}]},"Braccio2":{"rgba":[{"time":1,"color":"ffffffff"},{"time":2,"color":"ffffff00"}]},"Ear":{"rgba":[{"time":1,"color":"ffffffff"},{"time":2,"color":"ffffff00"}]},"Ear2":{"rgba":[{"time":1,"color":"858585ff"},{"time":2,"color":"85858500"}]},"Eye":{"rgba":[{"time":1,"color":"ffffffff"},{"time":2,"color":"ffffff00"}]},"Eye2":{"rgba":[{"time":1,"color":"ffffffff"},{"time":2,"color":"ffffff00"}]},"Gamba":{"rgba":[{"time":1,"color":"ffffffff"},{"time":2,"color":"ffffff00"}]},"Gamba2":{"rgba":[{"time":1,"color":"ffffffff"},{"time":2,"color":"ffffff00"}]},"Lance":{"rgba":[{"time":0.1667,"color":"858585ff","curve":"stepped"},{"time":1,"color":"858585ff"},{"time":2,"color":"85858500"}]},"Mano":{"rgba":[{"time":0.1667,"color":"858585ff","curve":"stepped"},{"time":1,"color":"858585ff"},{"time":2,"color":"85858500"}]},"Mano2":{"rgba":[{"time":1,"color":"ffffffff"},{"time":2,"color":"ffffff00"}]},"Nose":{"rgba":[{"time":1,"color":"ffffffff"},{"time":2,"color":"ffffff00"}]},"Piede":{"rgba":[{"time":1,"color":"ffffffff"},{"time":2,"color":"ffffff00"}]},"Piede2":{"rgba":[{"time":1,"color":"ffffffff"},{"time":2,"color":"ffffff00"}]},"Samurai/ArmorArm":{"rgba":[{"time":1,"color":"ffffffff"},{"time":2,"color":"ffffff00"}]},"Samurai/ArmorArm2":{"rgba":[{"time":1,"color":"ffffffff"},{"time":2,"color":"ffffff00"}]},"Samurai/ArmorGamba":{"rgba":[{"time":1,"color":"ffffffff"},{"time":2,"color":"ffffff00"}]},"Samurai/ArmorGamba2":{"rgba":[{"time":1,"color":"ffffffff"},{"time":2,"color":"ffffff00"}]},"Samurai/Helm":{"rgba":[{"time":1,"color":"ffffffff"},{"time":2,"color":"ffffff00"}]},"Samurai/Helm1":{"rgba":[{"time":1,"color":"ffffffff"},{"time":2,"color":"ffffff00"}]},"Samurai/Helm2":{"rgba":[{"time":1,"color":"858585ff"},{"time":2,"color":"85858500"}]},"Skirt":{"rgba":[{"time":1,"color":"ffffffff"},{"time":2,"color":"ffffff00"}]},"T3/Band2":{"rgba":[{"time":1,"color":"ffffffff"},{"time":2,"color":"ffffff00"}]},"Tail":{"rgba":[{"time":1,"color":"ffffffff"},{"time":2,"color":"ffffff00"}]},"Testa":{"rgba":[{"time":1,"color":"ffffffff"},{"time":2,"color":"ffffff00"}]}},"bones":{"LArm":{"rotate":[{},{"time":0.1667,"value":-32.67},{"time":0.3333,"value":-42.08}],"translate":[{},{"time":0.3333,"x":-2.21,"y":3.97}]},"Body3":{"rotate":[{"value":13.02}]},"Body2":{"rotate":[{"value":13.03},{"time":0.1667,"value":42.66}]},"Head":{"rotate":[{"value":-8.24},{"time":0.1667,"value":27.78},{"time":0.3333,"value":-35.55}]},"Ears":{"rotate":[{},{"time":0.1667,"value":33.34},{"time":0.3333,"value":10.77}]},"RArm":{"rotate":[{},{"time":0.1667,"value":-81.39},{"time":0.3333,"value":-0.59}]},"Body":{"rotate":[{},{"time":0.1667,"value":-44.38},{"time":0.3333,"value":-114.04}],"translate":[{"y":-10.97},{"time":0.1667,"y":10.5},{"time":0.3333,"y":-78.85}]},"Ears2":{"rotate":[{},{"time":0.1667,"value":51.47},{"time":0.3333,"value":-14.18}]},"LArm2":{"rotate":[{},{"time":0.1667,"value":-72.03}],"translate":[{},{"time":0.1667,"x":8.5}]},"RArm2":{"rotate":[{},{"time":0.3333,"value":74.84}]},"Tail2":{"rotate":[{"value":12.58}]},"Tail3":{"rotate":[{"value":12.58}]},"RLeg":{"rotate":[{"value":-18.07},{"time":0.8333,"value":7.23}]},"LLeg":{"rotate":[{"value":-26.1},{"time":0.8333,"value":46.64}]},"LLeg2":{"rotate":[{"value":16.11},{"time":0.8333,"value":-2.6}]},"Tail":{"rotate":[{"value":12.58},{"time":0.1667,"value":79.62},{"time":0.3333,"value":-15.61}]},"Lance":{"rotate":[{"value":70.13},{"time":0.3333,"value":74.02}],"translate":[{"x":-49.72,"y":25.02},{"time":0.3333,"x":99.19,"y":-89.87}]},"Skirt2":{"translate":[{},{"time":0.3333,"x":12.22,"y":-9.61}]},"LIK":{"translate":[{"x":-35.96,"y":-3.08},{"time":0.1667,"x":-61.85,"y":67.45},{"time":0.3333,"x":-91.74,"y":-1.63}]},"RLeg2":{"rotate":[{"value":51.1},{"time":0.8333,"value":94.09}]},"root":{"translate":[{"y":0.86}]},"RIK":{"translate":[{"x":49.22,"y":-10.33},{"time":0.1667,"x":-55.79,"y":26.22},{"time":0.3333,"x":-93.95,"y":-1.81}]}},"drawOrder":[{"offsets":[{"slot":"Lance","offset":17}]}],"events":[{"time":1.9833,"name":"destroyEnemyGameObject"}]},"die2":{"slots":{"Beard":{"rgba":[{"time":1,"color":"ffffffff"},{"time":2,"color":"ffffff00"}]},"Body":{"rgba":[{"time":1,"color":"ffffffff"},{"time":2,"color":"ffffff00"}]},"Braccio":{"rgba":[{"color":"858585ff","curve":"stepped"},{"time":1,"color":"858585ff"},{"time":2,"color":"85858500"}]},"Braccio2":{"rgba":[{"time":1,"color":"ffffffff"},{"time":2,"color":"ffffff00"}]},"Ear":{"rgba":[{"time":1,"color":"ffffffff"},{"time":2,"color":"ffffff00"}]},"Ear2":{"rgba":[{"time":1,"color":"858585ff"},{"time":2,"color":"85858500"}]},"Eye":{"rgba":[{"time":1,"color":"ffffffff"},{"time":2,"color":"ffffff00"}]},"Eye2":{"rgba":[{"time":1,"color":"ffffffff"},{"time":2,"color":"ffffff00"}]},"Gamba":{"rgba":[{"time":1,"color":"ffffffff"},{"time":2,"color":"ffffff00"}]},"Gamba2":{"rgba":[{"time":1,"color":"ffffffff"},{"time":2,"color":"ffffff00"}]},"Lance":{"rgba":[{"time":1,"color":"858585ff"},{"time":2,"color":"85858500"}]},"Mano":{"rgba":[{"color":"858585ff","curve":"stepped"},{"time":1,"color":"858585ff"},{"time":2,"color":"85858500"}]},"Mano2":{"rgba":[{"time":1,"color":"ffffffff"},{"time":2,"color":"ffffff00"}]},"Nose":{"rgba":[{"time":1,"color":"ffffffff"},{"time":2,"color":"ffffff00"}]},"Piede":{"rgba":[{"time":1,"color":"ffffffff"},{"time":2,"color":"ffffff00"}]},"Piede2":{"rgba":[{"time":1,"color":"ffffffff"},{"time":2,"color":"ffffff00"}]},"Samurai/ArmorArm":{"rgba":[{"time":1,"color":"ffffffff"},{"time":2,"color":"ffffff00"}]},"Samurai/ArmorArm2":{"rgba":[{"time":1,"color":"ffffffff"},{"time":2,"color":"ffffff00"}]},"Samurai/ArmorGamba":{"rgba":[{"time":1,"color":"ffffffff"},{"time":2,"color":"ffffff00"}]},"Samurai/ArmorGamba2":{"rgba":[{"time":1,"color":"ffffffff"},{"time":2,"color":"ffffff00"}]},"Samurai/Helm":{"rgba":[{"time":1,"color":"ffffffff"},{"time":2,"color":"ffffff00"}]},"Samurai/Helm1":{"rgba":[{"time":1,"color":"ffffffff"},{"time":2,"color":"ffffff00"}]},"Samurai/Helm2":{"rgba":[{"time":1,"color":"858585ff"},{"time":2,"color":"85858500"}]},"Skirt":{"rgba":[{"time":1,"color":"ffffffff"},{"time":2,"color":"ffffff00"}]},"T3/Band2":{"rgba":[{"time":1,"color":"ffffffff"},{"time":2,"color":"ffffff00"}]},"Tail":{"rgba":[{"time":1,"color":"ffffffff"},{"time":2,"color":"ffffff00"}]},"Testa":{"rgba":[{"time":1,"color":"ffffffff"},{"time":2,"color":"ffffff00"}]}},"bones":{"root":{"translate":[{"y":0.86}]},"Body":{"rotate":[{},{"time":0.1667,"value":-53.01},{"time":0.3333,"value":-13.58}],"translate":[{"y":-10.97},{"time":0.1667,"y":13.28},{"time":0.3333,"x":-26.33,"y":-83.72}]},"Body3":{"rotate":[{"value":13.02},{"time":0.3333,"value":56.52}]},"Body2":{"rotate":[{"value":13.03},{"time":0.3333,"value":59.01}]},"Head":{"rotate":[{"value":-8.24},{"time":0.1667,"value":-20.74},{"time":0.3333,"value":34.83}]},"LArm":{"rotate":[{},{"time":0.1667,"value":-145.03},{"time":0.3333,"value":-99.77}]},"LArm2":{"rotate":[{},{"time":0.3333,"value":0.21}],"translate":[{},{"time":0.3333,"x":7.05}]},"RArm":{"rotate":[{},{"time":0.1667,"value":-116.11},{"time":0.3333,"value":-87.22}],"translate":[{},{"time":0.3333,"x":4.4,"y":-30.89}]},"RArm2":{"rotate":[{},{"time":0.3333,"value":17.76}]},"RLeg":{"rotate":[{"value":-18.07}]},"RLeg2":{"rotate":[{"value":51.1}]},"LLeg":{"rotate":[{"value":-26.1}]},"LLeg2":{"rotate":[{"value":16.11}]},"Tail":{"rotate":[{"value":12.58},{"time":0.1667,"value":83.58},{"time":0.3333,"value":3.77}]},"Tail2":{"rotate":[{"value":12.58},{"time":0.1667,"value":43.32},{"time":0.3333,"value":86.71}]},"Tail3":{"rotate":[{"value":12.58},{"time":0.1667,"value":44.33},{"time":0.3333,"value":9.3}]},"Tail4":{"rotate":[{},{"time":0.1667,"value":21.6},{"time":0.3333,"value":-10.03}]},"Lance":{"rotate":[{"value":70.13},{"time":0.3333,"value":58.96}],"translate":[{"x":-49.72,"y":25.02},{"time":0.3333,"x":-14.35,"y":-32.32}]},"Skirt2":{"rotate":[{},{"time":0.3333,"value":-65.46}],"translate":[{},{"time":0.1667,"x":14.72,"y":11.57},{"time":0.3333,"x":26.76,"y":13.24}]},"Skirt":{"rotate":[{},{"time":0.3333,"value":-18.45}],"translate":[{},{"time":0.3333,"x":0.98,"y":2.13}]},"RIK":{"translate":[{"x":49.22,"y":-10.33},{"time":0.1667,"x":-11.87,"y":8.5},{"time":0.3333,"x":-142.48,"y":-6.08}]},"LIK":{"translate":[{"x":-35.96,"y":-3.08},{"time":0.1667,"x":-56.46,"y":67.77},{"time":0.3333,"x":-84.94,"y":5.68}]}},"drawOrder":[{"offsets":[{"slot":"Lance","offset":17}]}],"events":[{"time":1.9833,"name":"destroyEnemyGameObject"}]},"die3":{"slots":{"Beard":{"rgba":[{"time":1,"color":"ffffffff"},{"time":2,"color":"ffffff00"}]},"Body":{"rgba":[{"time":1,"color":"ffffffff"},{"time":2,"color":"ffffff00"}]},"Braccio":{"rgba":[{"color":"858585ff","curve":"stepped"},{"time":1,"color":"858585ff"},{"time":2,"color":"85858500"}]},"Braccio2":{"rgba":[{"time":1,"color":"ffffffff"},{"time":2,"color":"ffffff00"}]},"Ear":{"rgba":[{"time":1,"color":"ffffffff"},{"time":2,"color":"ffffff00"}]},"Ear2":{"rgba":[{"time":1,"color":"858585ff"},{"time":2,"color":"85858500"}]},"Eye":{"rgba":[{"time":1,"color":"ffffffff"},{"time":2,"color":"ffffff00"}]},"Eye2":{"rgba":[{"time":1,"color":"ffffffff"},{"time":2,"color":"ffffff00"}]},"Gamba":{"rgba":[{"time":1,"color":"ffffffff"},{"time":2,"color":"ffffff00"}]},"Gamba2":{"rgba":[{"time":1,"color":"ffffffff"},{"time":2,"color":"ffffff00"}]},"Lance":{"rgba":[{"time":1,"color":"858585ff"},{"time":2,"color":"85858500"}]},"Mano":{"rgba":[{"color":"858585ff","curve":"stepped"},{"time":1,"color":"858585ff"},{"time":2,"color":"85858500"}]},"Mano2":{"rgba":[{"time":1,"color":"ffffffff"},{"time":2,"color":"ffffff00"}]},"Nose":{"rgba":[{"time":1,"color":"ffffffff"},{"time":2,"color":"ffffff00"}]},"Piede":{"rgba":[{"time":1,"color":"ffffffff"},{"time":2,"color":"ffffff00"}]},"Piede2":{"rgba":[{"time":1,"color":"ffffffff"},{"time":2,"color":"ffffff00"}]},"Samurai/ArmorArm":{"rgba":[{"time":1,"color":"ffffffff"},{"time":2,"color":"ffffff00"}]},"Samurai/ArmorArm2":{"rgba":[{"time":1,"color":"ffffffff"},{"time":2,"color":"ffffff00"}]},"Samurai/ArmorGamba":{"rgba":[{"time":1,"color":"ffffffff"},{"time":2,"color":"ffffff00"}]},"Samurai/ArmorGamba2":{"rgba":[{"time":1,"color":"ffffffff"},{"time":2,"color":"ffffff00"}]},"Samurai/Helm":{"rgba":[{"time":1,"color":"ffffffff"},{"time":2,"color":"ffffff00"}]},"Samurai/Helm1":{"rgba":[{"time":1,"color":"ffffffff"},{"time":2,"color":"ffffff00"}]},"Samurai/Helm2":{"rgba":[{"time":1,"color":"858585ff"},{"time":2,"color":"85858500"}]},"Skirt":{"rgba":[{"time":1,"color":"ffffffff"},{"time":2,"color":"ffffff00"}]},"T3/Band2":{"rgba":[{"time":1,"color":"ffffffff"},{"time":2,"color":"ffffff00"}]},"Tail":{"rgba":[{"time":1,"color":"ffffffff"},{"time":2,"color":"ffffff00"}]},"Testa":{"rgba":[{"time":1,"color":"ffffffff"},{"time":2,"color":"ffffff00"}]}},"bones":{"root":{"translate":[{"y":0.86}]},"Body":{"rotate":[{},{"time":0.5,"value":-175.72}],"translate":[{"y":-10.97},{"time":0.1667,"x":-8.9,"y":41.54},{"time":0.5,"x":-27.77,"y":11.34}]},"Body3":{"rotate":[{"value":13.02}]},"Body2":{"rotate":[{"value":13.03},{"time":0.1667,"value":-22.66},{"time":0.5,"value":21.68}]},"Head":{"rotate":[{"value":-8.24},{"time":0.5,"value":48.3}]},"LArm":{"rotate":[{},{"time":0.1667,"value":61.39},{"time":0.5,"value":49.55}],"translate":[{},{"time":0.5,"x":-1.84,"y":5.6}]},"RArm":{"rotate":[{},{"time":0.1667,"value":-42.47},{"time":0.5,"value":-116.87}]},"RLeg":{"rotate":[{"value":-18.07}]},"RLeg2":{"rotate":[{"value":51.1}]},"LLeg":{"rotate":[{"value":-26.1}]},"LLeg2":{"rotate":[{"value":16.11}]},"Tail":{"rotate":[{"value":12.58},{"time":0.1667,"value":38.32},{"time":0.25,"value":1.07},{"time":0.5,"value":53.51}]},"Tail2":{"rotate":[{"value":12.58},{"time":0.1667,"value":38.32},{"time":0.25,"value":1.07},{"time":0.5,"value":53.51}]},"Tail3":{"rotate":[{"value":12.58},{"time":0.1667,"value":38.32},{"time":0.25,"value":1.07},{"time":0.5,"value":53.51}]},"Tail4":{"rotate":[{},{"time":0.1667,"value":25.74},{"time":0.25,"value":-11.5},{"time":0.5,"value":40.93}]},"Lance":{"rotate":[{"value":70.13}],"translate":[{"x":-49.72,"y":25.02},{"time":0.5,"x":-149.76,"y":135.4}]},"Skirt2":{"translate":[{},{"time":0.1667,"x":7.1,"y":10.28}]},"Skirt":{"rotate":[{},{"time":0.1667,"value":19.2}],"translate":[{},{"time":0.1667,"x":9.05,"y":-10}]},"RIK":{"translate":[{"x":49.22,"y":-10.33},{"time":0.1667,"x":10.72,"y":59.88},{"time":0.25,"x":-103.96,"y":74.75},{"time":0.3333,"x":-103.49,"y":185.97},{"time":0.5,"x":-115.05,"y":102.18}]},"LIK":{"translate":[{"x":-35.96,"y":-3.08},{"time":0.1667,"x":-42.07,"y":54.33},{"time":0.25,"x":-65.13,"y":134.63},{"time":0.3333,"x":-50.21,"y":230.35},{"time":0.5,"x":17.25,"y":193.55}]}},"drawOrder":[{"offsets":[{"slot":"Lance","offset":17}]}],"events":[{"time":1.9833,"name":"destroyEnemyGameObject"}]},"guard":{"slots":{"Braccio":{"rgba":[{"color":"858585ff"}]},"Mano":{"rgba":[{"color":"858585ff"}]}},"bones":{"LArm":{"rotate":[{"value":-91.95}],"translate":[{"x":-7.21,"y":2.14}]},"Head":{"rotate":[{"value":-8.24}]},"Ears":{"rotate":[{"value":-57.87},{"time":0.25,"value":-44.29},{"time":0.5,"value":-57.87}]},"Eye":{"translate":[{"x":-5.33}]},"Body":{"rotate":[{"value":3.49}],"translate":[{"y":-27.6}]},"Body3":{"rotate":[{"value":16.51},{"time":0.25,"value":5.18},{"time":0.5,"value":16.51}]},"Body2":{"rotate":[{"value":33.58},{"time":0.25,"value":50.71},{"time":0.5,"value":33.58}]},"Ears2":{"rotate":[{"value":-32.83},{"time":0.25,"value":-19.24},{"time":0.5,"value":-32.83}]},"Eye2":{"translate":[{"x":-7.41,"y":2.29}]},"LArm2":{"rotate":[{"value":-14.03}],"translate":[{"x":6.6}]},"RArm":{"rotate":[{"value":-112.69}],"translate":[{"x":11.05}]},"RArm2":{"rotate":[{"value":-46.71}],"translate":[{"x":4.27}]},"RLeg":{"rotate":[{"value":-18.07}]},"LLeg":{"rotate":[{"value":-26.1}]},"Tail":{"rotate":[{"value":48.25},{"time":0.25,"value":31.86},{"time":0.5,"value":48.25}]},"Tail2":{"rotate":[{"value":62.58},{"time":0.25,"value":46.19},{"time":0.5,"value":62.58}]},"Skirt2":{"rotate":[{"value":-37.74},{"time":0.25,"value":-22.87},{"time":0.5,"value":-37.74}],"translate":[{"x":16.86,"y":17.12},{"time":0.25,"x":10.28,"y":10.91},{"time":0.5,"x":16.86,"y":17.12}]},"Tail3":{"rotate":[{"value":62.58},{"time":0.25,"value":46.19},{"time":0.5,"value":62.58}]},"Lance":{"rotate":[{"value":138.44}],"translate":[{"x":-101.22,"y":-58.2}]},"RLeg2":{"rotate":[{"value":51.1}]},"LLeg2":{"rotate":[{"value":16.11}]},"Tail4":{"rotate":[{"value":27.26},{"time":0.25,"value":10.87},{"time":0.5,"value":27.26}]},"RIK":{"translate":[{"x":61.33,"y":-4.75}]},"LIK":{"translate":[{"x":-35.96,"y":-3.08}]},"root":{"translate":[{"y":0.86}]}},"drawOrder":[{"offsets":[{"slot":"Lance","offset":17}]}]},"hurt":{"slots":{"Body":{"rgba":[{"color":"ffffffff"},{"time":0.0833,"color":"ff0000ff"},{"time":0.6667,"color":"ffffffff"}]},"Braccio":{"rgba":[{"color":"858585ff"},{"time":0.0833,"color":"ff0000ff"},{"time":0.6667,"color":"858585ff"}]},"Braccio2":{"rgba":[{"color":"ffffffff"},{"time":0.0833,"color":"ff0000ff"},{"time":0.6667,"color":"ffffffff"}]},"Ear":{"rgba":[{"color":"ffffffff"},{"time":0.0833,"color":"ff0000ff"},{"time":0.6667,"color":"ffffffff"}]},"Ear2":{"rgba":[{"color":"858585ff"},{"time":0.0833,"color":"ff0000ff"},{"time":0.6667,"color":"858585ff"}]},"Eye":{"rgba":[{"color":"ffffffff"},{"time":0.0833,"color":"ff0000ff"},{"time":0.6667,"color":"ffffffff"}]},"Eye2":{"rgba":[{"color":"ffffffff"},{"time":0.0833,"color":"ff0000ff"},{"time":0.6667,"color":"ffffffff"}]},"Gamba":{"rgba":[{"color":"ffffffff"},{"time":0.0833,"color":"ff0000ff"},{"time":0.6667,"color":"ffffffff"}]},"Gamba2":{"rgba":[{"color":"ffffffff"},{"time":0.0833,"color":"ff0000ff"},{"time":0.6667,"color":"ffffffff"}]},"Lance":{"rgba":[{"color":"ffffffff"},{"time":0.0833,"color":"ff0000ff"},{"time":0.6667,"color":"ffffffff"}]},"Mano":{"rgba":[{"color":"858585ff"},{"time":0.0833,"color":"ff0000ff"},{"time":0.6667,"color":"858585ff"}]},"Mano2":{"rgba":[{"color":"ffffffff"},{"time":0.0833,"color":"ff0000ff"},{"time":0.6667,"color":"ffffffff"}]},"Nose":{"rgba":[{"color":"ffffffff"},{"time":0.0833,"color":"ff0000ff"},{"time":0.6667,"color":"ffffffff"}]},"Piede":{"rgba":[{"color":"ffffffff"},{"time":0.0833,"color":"ff0000ff"},{"time":0.6667,"color":"ffffffff"}]},"Piede2":{"rgba":[{"color":"ffffffff"},{"time":0.0833,"color":"ff0000ff"},{"time":0.6667,"color":"ffffffff"}]},"Samurai/ArmorArm":{"rgba":[{"color":"ffffffff"},{"time":0.0833,"color":"ff0000ff"},{"time":0.6667,"color":"ffffffff"}]},"Samurai/ArmorArm2":{"rgba":[{"color":"ffffffff"},{"time":0.0833,"color":"ff0000ff"},{"time":0.6667,"color":"ffffffff"}]},"Samurai/ArmorGamba":{"rgba":[{"color":"ffffffff"},{"time":0.0833,"color":"ff0000ff"},{"time":0.6667,"color":"ffffffff"}]},"Samurai/ArmorGamba2":{"rgba":[{"color":"ffffffff"},{"time":0.0833,"color":"ff0000ff"},{"time":0.6667,"color":"ffffffff"}]},"Samurai/Helm":{"rgba":[{"color":"ffffffff"},{"time":0.0833,"color":"ff0000ff"},{"time":0.6667,"color":"ffffffff"}]},"Samurai/Helm1":{"rgba":[{"color":"ffffffff"},{"time":0.0833,"color":"ff0000ff"},{"time":0.6667,"color":"ffffffff"}]},"Samurai/Helm2":{"rgba":[{"color":"858585ff"},{"time":0.0833,"color":"ff0000ff"},{"time":0.6667,"color":"858585ff"}]},"Skirt":{"rgba":[{"color":"ffffffff"},{"time":0.0833,"color":"ff0000ff"},{"time":0.6667,"color":"ffffffff"}]},"T3/Band2":{"rgba":[{"color":"ffffffff"},{"time":0.0833,"color":"ff0000ff"},{"time":0.6667,"color":"ffffffff"}]},"Tail":{"rgba":[{"color":"ffffffff"},{"time":0.0833,"color":"ff0000ff"},{"time":0.6667,"color":"ffffffff"}]},"Testa":{"rgba":[{"color":"ffffffff"},{"time":0.0833,"color":"ff0000ff"},{"time":0.6667,"color":"ffffffff"}]}},"bones":{"Lance":{"rotate":[{"value":70.13},{"time":0.0833,"value":82.27},{"time":0.6667,"value":70.13}],"translate":[{"x":-49.72,"y":25.02},{"time":0.0833,"x":-58.35,"y":14.43},{"time":0.6667,"x":-49.72,"y":25.02}]},"root":{"translate":[{"y":0.86}]},"Body":{"rotate":[{},{"time":0.0833,"value":-34.77},{"time":0.6667}],"translate":[{"y":-10.97}]},"Body3":{"rotate":[{"value":13.02}]},"Body2":{"rotate":[{"value":13.02},{"time":0.0833,"value":41.11},{"time":0.6667,"value":13.02}]},"Head":{"rotate":[{"value":-8.24},{"time":0.0833,"value":20.73},{"time":0.6667,"value":-8.24}]},"Ears":{"rotate":[{},{"time":0.0833,"value":-16.94},{"time":0.6667}]},"Ears2":{"rotate":[{},{"time":0.0833,"value":20.25},{"time":0.6667}]},"Eye":{"scale":[{},{"time":0.0833,"x":1.716},{"time":0.6667}]},"Eye2":{"scale":[{},{"time":0.0833,"x":1.716},{"time":0.6667}]},"LArm":{"rotate":[{},{"time":0.0833,"value":-22.31},{"time":0.6667}]},"RArm":{"rotate":[{},{"time":0.0833,"value":-22.31},{"time":0.6667}]},"RLeg":{"rotate":[{"value":-18.07},{"time":0.0833,"value":13.4},{"time":0.6667,"value":-18.07}]},"RLeg2":{"rotate":[{"value":51.1},{"time":0.0833,"value":69.46},{"time":0.6667,"value":51.1}]},"LLeg":{"rotate":[{"value":-26.1},{"time":0.0833,"value":-28.26},{"time":0.6667,"value":-26.1}]},"LLeg2":{"rotate":[{"value":16.11},{"time":0.0833,"value":70.19},{"time":0.6667,"value":16.11}]},"Tail":{"rotate":[{"value":12.58},{"time":0.0833,"value":62.21},{"time":0.6667,"value":12.58}]},"Tail2":{"rotate":[{"value":12.58},{"time":0.0833,"value":62.21},{"time":0.6667,"value":12.58}]},"Tail3":{"rotate":[{"value":12.58},{"time":0.0833,"value":62.21},{"time":0.6667,"value":12.58}]},"Tail4":{"rotate":[{},{"time":0.0833,"value":34.59},{"time":0.6667}]},"Skirt2":{"rotate":[{"value":-22.03},{"time":0.0333,"value":-35.8},{"time":0.0833,"value":-33.11},{"time":0.6667,"value":-27.97}],"translate":[{"x":8.43,"y":12.16},{"time":0.0333,"x":6.76,"y":18.97},{"time":0.0833,"x":0.33,"y":17.43},{"time":0.6667,"x":9.45,"y":13.08}]},"Skirt":{"rotate":[{"value":-17.53},{"time":0.0833},{"time":0.6667,"value":-25.06}],"translate":[{"x":-8.47,"y":10.77},{"time":0.0833,"x":-11.7,"y":-3.51},{"time":0.6667,"x":-12.64,"y":7.18}]},"LIK":{"translate":[{"x":-35.96,"y":-3.08},{"time":0.0833,"x":-54.29,"y":34.86},{"time":0.6667,"x":-35.96,"y":-3.08}]}},"attachments":{"Thief/Thief1":{"Skirt":{"Skirt":{"deform":[{"offset":36,"vertices":[4.72433,-0.03707,4.65793,-0.78946]}]}}}},"drawOrder":[{"offsets":[{"slot":"Lance","offset":17}]}]},"idle":{"slots":{"Braccio":{"rgba":[{"color":"858585ff"}]},"Lance":{"rgba":[{"color":"858585ff"}]},"Mano":{"rgba":[{"color":"858585ff"}]}},"bones":{"root":{"translate":[{"y":0.86}]},"Body2":{"rotate":[{},{"time":1,"value":4.5},{"time":2}],"translate":[{},{"time":1,"x":5.76},{"time":2}]},"Head":{"rotate":[{},{"time":1,"value":3.12},{"time":2}]},"Ears":{"rotate":[{},{"time":1,"value":7.94},{"time":2}]},"Ears2":{"rotate":[{},{"time":1,"value":16.68},{"time":2}]},"Eye":{"translate":[{},{"time":1,"x":2.49},{"time":2}]},"Eye2":{"translate":[{},{"time":1,"x":2.49},{"time":2}]},"Nose":{"translate":[{},{"time":1,"x":2},{"time":2}]},"LArm":{"rotate":[{},{"time":1,"value":2.51},{"time":2}],"translate":[{},{"time":1,"x":2.23,"y":1.66},{"time":2}]},"RArm":{"rotate":[{},{"time":1,"value":-5.36},{"time":2}],"translate":[{},{"time":1,"x":-5.16},{"time":2}]},"RLeg":{"rotate":[{},{"time":1},{"time":2}]},"RLeg2":{"rotate":[{},{"time":1},{"time":2}]},"LLeg":{"rotate":[{},{"time":1},{"time":2}]},"LLeg2":{"rotate":[{},{"time":1},{"time":2}]},"Tail":{"rotate":[{},{"time":1,"value":13.11},{"time":2}]},"Tail2":{"rotate":[{},{"time":1,"value":13.11},{"time":2}]},"Tail3":{"rotate":[{},{"time":1,"value":13.11},{"time":2}]},"Tail4":{"rotate":[{},{"time":1,"value":13.11},{"time":2}]},"Skirt2":{"translate":[{},{"time":1,"x":-5.69},{"time":2}]},"Skirt":{"translate":[{},{"time":1,"x":-6.89},{"time":2}]}}},"idle_battle":{"slots":{"Braccio":{"rgba":[{"color":"858585ff"}]},"Mano":{"rgba":[{"color":"858585ff"}]}},"bones":{"Body3":{"rotate":[{"value":13.02}]},"Body2":{"rotate":[{"value":13.03},{"time":1,"value":18.92},{"time":2,"value":13.03}],"translate":[{},{"time":1,"x":-5.17,"y":3.92},{"time":2}]},"Head":{"rotate":[{"value":-8.24},{"time":1,"value":-11.56},{"time":2,"value":-8.24}]},"Ears":{"rotate":[{},{"time":1,"value":-17.68},{"time":2}]},"Eye":{"translate":[{},{"time":1,"x":-3.48,"y":0.17},{"time":2}]},"Tail4":{"rotate":[{},{"time":1,"value":33.1},{"time":2}]},"Body":{"translate":[{"y":-10.97}]},"Ears2":{"rotate":[{},{"time":1,"value":-14.84},{"time":2}]},"Eye2":{"translate":[{},{"time":1,"x":-3.6,"y":1.71},{"time":2}]},"Tail2":{"rotate":[{"value":12.58},{"time":1,"value":45.68},{"time":2,"value":12.58}]},"Tail3":{"rotate":[{"value":12.58},{"time":1,"value":45.68},{"time":2,"value":12.58}]},"RLeg":{"rotate":[{"value":-18.07}]},"LLeg":{"rotate":[{"value":-26.1}]},"LLeg2":{"rotate":[{"value":16.11}]},"Tail":{"rotate":[{"value":12.58}]},"Lance":{"rotate":[{"value":70.13}],"translate":[{"x":-49.72,"y":25.02}]},"Skirt2":{"rotate":[{"value":-16.54}],"translate":[{"x":5.68,"y":6.26}]},"Skirt":{"translate":[{},{"time":1,"x":-0.49,"y":-2.89},{"time":2}]},"LIK":{"translate":[{"x":-35.96,"y":-3.08}]},"RLeg2":{"rotate":[{"value":51.1}]},"root":{"translate":[{"y":0.86}]},"RIK":{"translate":[{"x":49.22,"y":-10.33}]}},"drawOrder":[{"offsets":[{"slot":"Lance","offset":17}]}]},"run":{"slots":{"Braccio":{"rgba":[{"color":"858585ff"}]},"Mano":{"rgba":[{"color":"858585ff"}]},"Samurai/ArmorGamba":{"rgba":[{"color":"858585ff"}]}},"bones":{"Body":{"rotate":[{"value":22.26}],"translate":[{"y":-11.99},{"time":0.0833,"y":3.63},{"time":0.25,"y":-17.45},{"time":0.3333,"y":-6.52},{"time":0.5,"y":-11.99}]},"Lance":{"rotate":[{"value":75.46}],"translate":[{"x":-50.79,"y":25.23}]},"RArm2":{"translate":[{"x":5.03,"y":-0.4}]},"Tail2":{"rotate":[{"value":12.3},{"time":0.25,"value":73.29},{"time":0.5,"value":12.3}]},"Tail3":{"rotate":[{"value":-3.89},{"time":0.25,"value":89.55},{"time":0.5,"value":-3.89}]},"Tail4":{"rotate":[{"value":-41.57},{"time":0.25,"value":32.28},{"time":0.5,"value":-41.57}]},"Body2":{"rotate":[{"value":-6.68},{"time":0.25,"value":-25.16},{"time":0.5,"value":-6.68}]},"Body3":{"rotate":[{"value":20.94}]},"RIK":{"translate":[{"x":41.95,"y":36.46},{"time":0.0833,"x":2.92,"y":36.46},{"time":0.1667,"x":-90.5,"y":7.22},{"time":0.25,"x":-35.86,"y":1.76},{"time":0.3333,"x":-2.79,"y":-8.8},{"time":0.4167,"x":67.37,"y":57.83},{"time":0.5,"x":41.95,"y":36.46}]},"Skirt2":{"rotate":[{"value":-49.95},{"time":0.4167,"value":-64.7},{"time":0.5,"value":-49.95}],"translate":[{"x":17.57,"y":20.68},{"time":0.25,"x":5.3,"y":3.05},{"time":0.4167,"x":28.08,"y":18.02},{"time":0.5,"x":17.57,"y":20.68}]},"Nose":{"translate":[{"x":1.66,"y":9.93}]},"Eye2":{"translate":[{"x":-2.64,"y":8.47}]},"Eye":{"translate":[{"x":-3.87,"y":7.75}]},"Ears":{"rotate":[{"value":-49.82},{"time":0.25,"value":-65.97},{"time":0.5,"value":-49.82}],"translate":[{"x":-0.56,"y":-5.34}]},"Ears2":{"rotate":[{"value":-34.86},{"time":0.25,"value":-46.25},{"time":0.5,"value":-34.86}],"translate":[{"x":8.99}]},"Head":{"rotate":[{},{"time":0.25,"value":-6.87},{"time":0.5}],"translate":[{"x":-0.31,"y":15.72},{"time":0.25,"x":-0.16,"y":17.6},{"time":0.5,"x":-0.31,"y":15.72}]},"LArm":{"rotate":[{},{"time":0.25,"value":-9.1},{"time":0.5}],"translate":[{"x":4.87,"y":7.13},{"time":0.25,"x":9.27,"y":9.58},{"time":0.5,"x":4.87,"y":7.13}]},"LArm2":{"rotate":[{},{"time":0.25,"value":-6.27},{"time":0.5}]},"RArm":{"rotate":[{},{"time":0.25,"value":-12.64},{"time":0.5}],"translate":[{},{"time":0.25,"x":17.07,"y":-19.18},{"time":0.5}]},"RLeg":{"rotate":[{"value":-17.31}]},"RLeg2":{"rotate":[{"value":88.05}]},"LLeg":{"rotate":[{"value":-45.5}]},"LLeg2":{"rotate":[{"value":65.77}]},"Tail":{"rotate":[{"value":19.76},{"time":0.25,"value":7.87},{"time":0.5,"value":19.76}]},"Skirt":{"rotate":[{"value":-29.02},{"time":0.25,"value":12.99},{"time":0.5,"value":-29.02}],"translate":[{"x":-4.54,"y":6.81},{"time":0.25,"x":-1.71,"y":-5.32},{"time":0.5,"x":-4.54,"y":6.81}]},"LIK":{"translate":[{},{"time":0.0833,"x":33.12,"y":-7.12},{"time":0.1667,"x":101.03,"y":-7.12},{"time":0.25,"x":86.32,"y":51.82},{"time":0.3333,"x":16.24,"y":43.14},{"time":0.4167,"x":-87.59,"y":15.04},{"time":0.5}]}},"attachments":{"Samurai/Samurai":{"Samurai/Helm":{"Samurai/Helm2":{"deform":[{"offset":4,"vertices":[1.06029,1.8254,0,0,0,0,0,0,0,0,0,0,-0.3586,11.92928]}]}}},"Thief/Thief1":{"Body":{"Body":{"deform":[{"offset":14,"vertices":[3.4108,10.1964,4.95231,9.54334,0,0,0,0,0,0,0,0,0,0,0,0,0,0,0,0,0,0,0,0,2.29186,17.21845,-1.12743,17.3336,0,0,0,0,-0.40884,17.36552,2.29186,17.21845,-0.40884,17.36552,2.29186,17.21845,-1.12743,17.3336]}]}},"Skirt":{"Skirt":{"deform":[{"offset":10,"vertices":[-8.78268,14.9865,-0.40884,17.36554,-3.97858,16.90858,0,0,0,0,0,0,0,0,0,0,0,0,0,0,0,0,-0.40884,17.36554,-3.97858,16.90858]}]}},"Testa":{"Testa":{"deform":[{"offset":14,"vertices":[0.24284,10.97251]}]}}}},"drawOrder":[{"offsets":[{"slot":"Lance","offset":17}]}]},"stun":{"slots":{"Braccio":{"rgba":[{"color":"858585ff"}]},"Lance":{"rgba":[{"color":"858585ff"}]},"Mano":{"rgba":[{"color":"858585ff"}]}},"bones":{"Body":{"translate":[{"y":-37.14}]},"RIK":{"translate":[{"x":37.14}]},"LIK":{"translate":[{"x":-56.4,"y":2.06}]},"Skirt2":{"rotate":[{"value":-54.64}],"translate":[{"x":24.25,"y":20.7},{"time":0.5,"x":17.66,"y":13.56},{"time":1,"x":24.25,"y":20.7}]},"Tail":{"rotate":[{"value":6.07}]},"Tail2":{"rotate":[{"value":6.07}]},"Tail3":{"rotate":[{"value":32.77}]},"Tail4":{"rotate":[{"value":27.49}]},"Lance":{"rotate":[{"value":-18.37}],"translate":[{"x":-19.92,"y":-26.64}]},"LArm":{"rotate":[{"value":-158.47},{"time":0.5,"value":-148.18},{"time":1,"value":-158.47}],"translate":[{"x":-14.13,"y":1.18}]},"LArm2":{"rotate":[{"value":-59.13}],"translate":[{"x":6.2,"y":1.14}]},"Ears":{"rotate":[{"value":-124.86}]},"Ears2":{"rotate":[{"value":127.35}]},"Body2":{"rotate":[{"value":31.13},{"time":0.5,"value":35.19},{"time":1,"value":31.13}]},"RArm":{"rotate":[{"value":-64.73}]},"Body3":{"rotate":[{"value":19.76},{"time":0.5,"value":4.18},{"time":1,"value":19.76}]},"Head":{"rotate":[{"value":-10.57},{"time":0.5,"value":8.68},{"time":1,"value":-10.57}]},"Skirt":{"translate":[{"x":-1.75,"y":8.78}]}}},"tired":{"slots":{"Braccio":{"rgba":[{"color":"858585ff"}]},"Lance":{"rgba":[{"color":"858585ff"}]},"Mano":{"rgba":[{"color":"858585ff"}]}},"bones":{"root":{"translate":[{"y":0.86}]},"Body":{"translate":[{"y":-16.51},{"time":0.5,"y":-20.63},{"time":1,"y":-16.51}]},"Body3":{"rotate":[{"value":30.81}]},"Body2":{"translate":[{},{"time":0.5,"x":7.18,"y":2.7},{"time":1}]},"Head":{"rotate":[{"value":26.07}],"translate":[{},{"time":0.5,"x":-7.48,"y":1.79},{"time":1}]},"Ears":{"rotate":[{"value":-102.18}]},"Ears2":{"rotate":[{"value":93.07}]},"Eye":{"rotate":[{"value":-30.85}]},"Eye2":{"rotate":[{"value":53}],"translate":[{"x":-3.82,"y":4.02}]},"LArm":{"rotate":[{"value":-116.61}],"translate":[{"x":-4.94,"y":7.83}]},"RArm":{"rotate":[{"value":-38.93}],"translate":[{"x":4.22,"y":-10.88}]},"RLeg":{"rotate":[{}]},"RLeg2":{"rotate":[{}]},"LLeg":{"rotate":[{}]},"LLeg2":{"rotate":[{}]},"Tail":{"rotate":[{"value":5.03}]},"Tail2":{"rotate":[{"value":22.13}]},"Tail4":{"rotate":[{"value":-22.48}]},"Lance":{"translate":[{"x":-9.07,"y":-14.61}]},"Skirt2":{"rotate":[{"value":-44.88}],"translate":[{"x":20.25,"y":19.97}]},"Skirt":{"rotate":[{"value":-27.75}],"translate":[{"x":-6.09,"y":23.46}]},"RIK":{"translate":[{"x":47.87,"y":-1.09}]},"LIK":{"translate":[{"x":-24.1,"y":0.83}]}},"drawOrder":[{"offsets":[{"slot":"Lance","offset":18}]}]},"walk":{"slots":{"Braccio":{"rgba":[{"color":"858585ff"}]},"Lance":{"rgba":[{"color":"858585ff"}]},"Mano":{"rgba":[{"color":"858585ff"}]},"Samurai/ArmorGamba":{"rgba":[{"color":"858585ff"}]}},"bones":{"RIK":{"translate":[{"x":19.4,"y":39.71},{"time":0.1667,"x":0.82,"y":39.11},{"time":0.3333,"x":-80.87,"y":4.63},{"time":0.5,"x":-39.49,"y":-0.39},{"time":0.5833,"x":-22.67,"y":-5.86},{"time":0.6667,"x":-5.86,"y":-11.33},{"time":0.8333,"x":17.93,"y":-14.09},{"time":1,"x":56.31,"y":12.81},{"time":1.1667,"x":19.4,"y":39.71}]},"LIK":{"translate":[{"x":4.25,"y":-0.57},{"time":0.1667,"x":9.11,"y":-4.76},{"time":0.3333,"x":39.09,"y":-4.94},{"time":0.5,"x":74.95,"y":31.93},{"time":0.5833,"x":51.61,"y":36.23},{"time":0.6667,"x":28.26,"y":40.53},{"time":0.8333,"x":-4.74,"y":40.53},{"time":1,"x":-74.41,"y":4.49},{"time":1.1667,"x":4.25,"y":-0.57}]},"Body":{"translate":[{"y":-13.8},{"time":0.1667,"y":-7.79},{"time":0.3333,"y":-9.51},{"time":0.5,"y":-13.8},{"time":0.5833,"y":-7.36},{"time":0.6667,"y":-0.91},{"time":0.8333,"y":-6.76},{"time":1,"y":-12.34},{"time":1.1667,"y":-13.8}]},"Body3":{"rotate":[{},{"time":0.5833,"value":8.08},{"time":1.1667}]},"Body2":{"rotate":[{},{"time":0.5833,"value":7.11},{"time":1.1667}]},"Head":{"translate":[{},{"time":0.5833,"x":0.36,"y":2.23},{"time":1.1667}]},"Ears":{"rotate":[{},{"time":0.5833,"value":-20.03},{"time":1.1667}],"translate":[{},{"time":0.5833,"y":3.69},{"time":1.1667}]},"Ears2":{"rotate":[{},{"time":0.5833,"value":-20.03},{"time":1.1667}],"translate":[{},{"time":0.5833,"y":-4.08},{"time":1.1667}]},"Eye":{"translate":[{},{"time":0.5833,"y":7.76},{"time":1.1667}]},"Eye2":{"translate":[{},{"time":0.5833,"y":6.96},{"time":1.1667}]},"Nose":{"translate":[{},{"time":0.5833,"x":1.25,"y":9.58},{"time":1.1667}]},"LArm":{"rotate":[{"value":6.14}],"translate":[{},{"time":0.5833,"x":4.75,"y":4.56},{"time":1.1667}]},"RArm2":{"rotate":[{"value":-47.56}],"translate":[{"x":3.86}]},"RLeg":{"rotate":[{"value":-13.11},{"time":0.5833,"value":-10.87},{"time":1.1667,"value":-13.11}]},"RLeg2":{"rotate":[{"value":119.86},{"time":0.5833,"value":-3.9},{"time":1.1667,"value":119.86}]},"LLeg":{"rotate":[{"value":-17.16},{"time":0.5833,"value":13.8},{"time":1.1667,"value":-17.16}]},"LLeg2":{"rotate":[{"value":58.64},{"time":0.5833,"value":82.94},{"time":1.1667,"value":58.64}]},"Tail":{"rotate":[{"value":23.69},{"time":0.5833,"value":-3.18},{"time":1.1667,"value":23.69}]},"Tail2":{"rotate":[{"value":23.69}]},"Tail3":{"rotate":[{"value":79.29}]},"Tail4":{"rotate":[{"value":23.69}]},"Lance":{"translate":[{"x":-28.51,"y":-60.78}]},"Skirt2":{"rotate":[{"time":0.5833},{"time":0.9167,"value":-30.73},{"time":1.1667}],"translate":[{"x":7.48,"y":2.09},{"time":0.5,"x":-8.06,"y":-1.25},{"time":0.5833,"x":-7.38,"y":-1.85},{"time":0.9167,"x":11.39,"y":12.9},{"time":1.1667,"x":7.48,"y":2.09}]},"Skirt":{"translate":[{"x":-0.99,"y":8.69},{"time":0.5,"y":4.24},{"time":0.5833,"x":-1.78,"y":-0.99},{"time":1.1667,"x":-0.99,"y":8.69}]}},"attachments":{"Thief/Thief1":{"Body":{"Body":{"deform":[{"offset":46,"vertices":[0.17665,1.04222,-0.04414,1.05616]},{"time":0.5833,"offset":46,"vertices":[1.25797,7.42269,0.59657,7.49563,1.51389,8.9326,0.89702,9.01525,1.28793,8.96809]},{"time":1.1667,"offset":46,"vertices":[0.17665,1.04222,-0.04414,1.05616]}]}},"Skirt":{"Skirt":{"deform":[{"offset":10,"vertices":[0.14424,0.85073,0.14418,0.85074,0.14421,0.85073,0,0,0,0,0,0,0,0,0,0,0,0,0,0,0,0,0.14418,0.85074,0.14421,0.85073]},{"time":0.5833,"offset":10,"vertices":[-2.94849,11.0016,-2.94868,11.00164,-2.94851,11.00159,0,0,0,0,0,0,0,0,0,0,0,0,0,0,0,0,-2.94868,11.00164,-2.94851,11.00159]},{"time":1.1667,"offset":10,"vertices":[0.14424,0.85073,0.14418,0.85074,0.14421,0.85073,0,0,0,0,0,0,0,0,0,0,0,0,0,0,0,0,0.14418,0.85074,0.14421,0.85073]}]}},"Testa":{"Testa":{"deform":[{"offset":14,"vertices":[-0.246,0.7795]},{"time":0.5833,"offset":14,"vertices":[-0.67764,11.39685]},{"time":1.1667,"offset":14,"vertices":[-0.246,0.7795]}]}}}},"drawOrder":[{"offsets":[{"slot":"Lance","offset":9}]}]},"attack_lunge/attack_lunge":{"slots":{"Braccio":{"rgba":[{"color":"858585ff"}]},"Mano":{"rgba":[{"color":"858585ff"}]}},"bones":{"Lance":{"rotate":[{"value":57.26},{"time":0.0667,"value":98.13},{"time":0.0833,"value":105.77},{"time":0.1,"value":109.4},{"time":0.1333,"value":91.61,"curve":"stepped"},{"time":0.3167,"value":91.61},{"time":0.5,"value":70.13}],"translate":[{"x":-55.09,"y":49.35},{"time":0.0667,"x":-47.27,"y":-3.97},{"time":0.0833,"x":-41.8,"y":-9.24},{"time":0.1,"x":-32.15,"y":-6.91},{"time":0.1333,"x":2.28,"y":-17.27,"curve":"stepped"},{"time":0.3167,"x":2.28,"y":-17.27},{"time":0.5,"x":-49.72,"y":25.02}]},"LArm":{"rotate":[{"value":7.05},{"time":0.1333,"value":-90.88,"curve":"stepped"},{"time":0.3167,"value":-90.88},{"time":0.5}],"translate":[{"x":-13.9,"y":0.36},{"time":0.1,"x":-8.25,"y":1.7},{"time":0.1333,"x":0.32,"y":1.41,"curve":"stepped"},{"time":0.3167,"x":0.32,"y":1.41},{"time":0.5}]},"Body3":{"rotate":[{"value":29.49},{"time":0.1333,"value":38.36,"curve":"stepped"},{"time":0.3167,"value":38.36},{"time":0.5,"value":13.02}],"translate":[{"x":-11.96,"y":4.81},{"time":0.1333,"x":-5.03,"y":6.15,"curve":"stepped"},{"time":0.3167,"x":-5.03,"y":6.15},{"time":0.5}]},"Body2":{"rotate":[{"value":49.22},{"time":0.1333,"value":-2.93,"curve":"stepped"},{"time":0.3167,"value":-2.93},{"time":0.5,"value":13.03}],"translate":[{"x":-20.08,"y":10.02},{"time":0.1333,"x":1.99,"y":4.03,"curve":"stepped"},{"time":0.3167,"x":1.99,"y":4.03},{"time":0.5}]},"Head":{"rotate":[{"value":-52.45},{"time":0.1333,"value":-7.23,"curve":"stepped"},{"time":0.3167,"value":-7.23},{"time":0.5,"value":-8.24}],"translate":[{"x":11.08,"y":1.34},{"time":0.1333,"x":-6.61,"y":13.42,"curve":"stepped"},{"time":0.3167,"x":-6.61,"y":13.42},{"time":0.5}]},"RArm":{"rotate":[{"value":-34.71},{"time":0.1333,"value":-75.37,"curve":"stepped"},{"time":0.3167,"value":-75.37},{"time":0.5}],"translate":[{},{"time":0.1,"x":12.22,"y":-5.95},{"time":0.1333,"x":15.53,"y":3.63,"curve":"stepped"},{"time":0.3167,"x":15.53,"y":3.63},{"time":0.5}]},"Tail4":{"rotate":[{},{"time":0.1333,"value":37.43,"curve":"stepped"},{"time":0.3167,"value":37.43},{"time":0.5}]},"Body":{"rotate":[{},{"time":0.3167,"value":11.62},{"time":0.5}],"translate":[{"y":-1.39},{"time":0.1333,"x":-23.39,"y":-32.93,"curve":"stepped"},{"time":0.3167,"x":-23.39,"y":-32.93},{"time":0.4,"x":-11.69,"y":-9.57},{"time":0.5,"y":-10.97}]},"LArm2":{"rotate":[{"value":-56.93},{"time":0.1,"value":-2.47},{"time":0.1333,"value":15.6,"curve":"stepped"},{"time":0.3167,"value":15.6},{"time":0.5}],"translate":[{"x":6.95},{"time":0.5}]},"RArm2":{"rotate":[{"value":38.78},{"time":0.1,"value":-31.86},{"time":0.1333,"value":27.25,"curve":"stepped"},{"time":0.3167,"value":27.25},{"time":0.5}],"translate":[{"x":2.85,"y":0.25},{"time":0.1,"x":6.92},{"time":0.5}]},"Tail2":{"rotate":[{"value":12.58},{"time":0.1333,"value":63.1,"curve":"stepped"},{"time":0.3167,"value":63.1},{"time":0.5,"value":12.58}]},"Tail3":{"rotate":[{"value":12.58},{"time":0.1333,"value":63.1,"curve":"stepped"},{"time":0.3167,"value":63.1},{"time":0.5,"value":12.58}]},"RLeg":{"rotate":[{"value":-18.07}]},"LLeg":{"rotate":[{"value":-26.1}]},"LLeg2":{"rotate":[{"value":16.11}]},"Tail":{"rotate":[{"value":12.58},{"time":0.1333,"value":63.1,"curve":"stepped"},{"time":0.3167,"value":63.1},{"time":0.5,"value":12.58}]},"LIK":{"translate":[{"x":12.78,"y":-8.99},{"time":0.1333,"x":54.17,"y":-7.56},{"time":0.3167,"x":54.17,"y":-6.87},{"time":0.4,"x":13.3,"y":29.44},{"time":0.5,"x":-35.96,"y":-3.08}]},"RLeg2":{"rotate":[{"value":51.1}]},"root":{"translate":[{"y":0.86}]},"RIK":{"translate":[{"x":7.21,"y":39.57},{"time":0.1333,"x":-53.34,"y":-0.06,"curve":"stepped"},{"time":0.3167,"x":-53.34,"y":-0.06},{"time":0.5,"x":49.22,"y":-10.33}]}},"events":[{"time":0.4667,"name":"endAttackPhase"}]},"attack_lunge/attack_lunge_loop":{"slots":{"Braccio":{"rgba":[{"color":"858585ff"}]},"Mano":{"rgba":[{"color":"858585ff"}]}},"bones":{"LArm":{"rotate":[{"value":-31.35},{"time":0.3333,"value":-32.87},{"time":0.6667,"value":-31.35}],"translate":[{"x":2.82,"y":-3.3}]},"Body3":{"rotate":[{"value":43.65},{"time":0.3333,"value":42.12},{"time":0.6667,"value":43.65}],"translate":[{"y":-14.69}]},"Body2":{"rotate":[{"value":12.81},{"time":0.3333,"value":11.29},{"time":0.6667,"value":12.81}],"translate":[{"x":-18.37,"y":-12.07}]},"Head":{"rotate":[{"value":-8.46},{"time":0.3333,"value":-9.99},{"time":0.6667,"value":-8.46}]},"Ears":{"rotate":[{"value":-0.22},{"time":0.3333,"value":-1.75},{"time":0.6667,"value":-0.22}]},"Eye":{"rotate":[{"value":-0.22},{"time":0.3333,"value":-1.75},{"time":0.6667,"value":-0.22}]},"Nose":{"rotate":[{"value":-0.22},{"time":0.3333,"value":-1.75},{"time":0.6667,"value":-0.22}]},"RArm":{"rotate":[{"value":-38.61},{"time":0.3333,"value":-40.13},{"time":0.6667,"value":-38.61}],"translate":[{"x":10.3,"y":-17.6}]},"Body":{"rotate":[{"value":-0.22},{"time":0.3333,"value":-1.75},{"time":0.6667,"value":-0.22}],"translate":[{"y":-20.67}]},"Ears2":{"rotate":[{"value":-0.22},{"time":0.3333,"value":-1.75},{"time":0.6667,"value":-0.22}]},"Eye2":{"rotate":[{"value":-0.22},{"time":0.3333,"value":-1.75},{"time":0.6667,"value":-0.22}]},"LArm2":{"rotate":[{"value":-0.22},{"time":0.3333,"value":-1.75},{"time":0.6667,"value":-0.22}]},"RArm2":{"rotate":[{"value":-0.22},{"time":0.3333,"value":-1.75},{"time":0.6667,"value":-0.22}],"translate":[{"x":2.85,"y":0.25}]},"Tail2":{"rotate":[{"value":12.36},{"time":0.3333,"value":10.83},{"time":0.6667,"value":12.36}]},"Tail3":{"rotate":[{"value":12.58}]},"RLeg":{"rotate":[{"value":-18.07}]},"LLeg":{"rotate":[{"value":-26.1}]},"LLeg2":{"rotate":[{"value":16.11}]},"Tail":{"rotate":[{"value":12.36},{"time":0.3333,"value":10.83},{"time":0.6667,"value":12.36}]},"Lance":{"rotate":[{"value":87.96},{"time":0.3333,"value":86.48},{"time":0.6667,"value":87.96}],"translate":[{"x":-66.11,"y":20.54},{"time":0.3333,"x":-69.29,"y":14.52},{"time":0.6667,"x":-66.11,"y":20.54}]},"Skirt2":{"rotate":[{"value":-73.95}],"translate":[{"x":36.67,"y":28.35}]},"Skirt":{"rotate":[{"value":-27.75}],"translate":[{"x":0.51,"y":33.47}]},"LIK":{"translate":[{"x":-35.96,"y":-3.08}]},"RLeg2":{"rotate":[{"value":51.1}]},"root":{"translate":[{"y":0.86}]},"RIK":{"translate":[{"x":44.98,"y":-2.42}]},"Beard":{"rotate":[{"value":-0.13},{"time":0.3333,"value":-1.75},{"time":0.6667,"value":-0.13}]},"band":{"rotate":[{"value":-0.13},{"time":0.3333,"value":-1.75},{"time":0.6667,"value":-0.13}]}},"drawOrder":[{"offsets":[{"slot":"Lance","offset":18}]}],"events":[{"name":"activeAtkBaloon"}]},"attack_lunge/attack_lunge_pre":{"slots":{"Braccio":{"rgba":[{"color":"858585ff"}]},"Mano":{"rgba":[{"color":"858585ff"}]}},"bones":{"LArm":{"rotate":[{"time":0.1667},{"time":0.3333,"value":-18.92},{"time":0.5,"value":-31.13}],"translate":[{"time":0.3333},{"time":0.5,"x":2.82,"y":-3.3}]},"Body3":{"rotate":[{"value":13.02,"curve":"stepped"},{"time":0.1667,"value":13.02},{"time":0.3333,"value":37.79},{"time":0.5,"value":43.86}],"translate":[{"time":0.3333},{"time":0.5,"y":-14.69}]},"Body2":{"rotate":[{"value":13.03}],"translate":[{"time":0.1667},{"time":0.3333,"x":-20.08,"y":10.02},{"time":0.5,"x":-18.37,"y":-12.07}]},"Head":{"rotate":[{"value":-8.24}]},"RArm":{"rotate":[{"time":0.1667},{"time":0.3333,"value":-23.62},{"time":0.5,"value":-38.39}],"translate":[{"time":0.3333},{"time":0.5,"x":10.3,"y":-17.6}]},"Body":{"translate":[{"y":-10.97,"curve":"stepped"},{"time":0.1667,"y":-10.97},{"time":0.3333,"y":-20.67}]},"RArm2":{"translate":[{"time":0.1667},{"time":0.3333,"x":2.85,"y":0.25}]},"Tail2":{"rotate":[{"value":12.58}]},"Tail3":{"rotate":[{"value":12.58}]},"RLeg":{"rotate":[{"value":-18.07}]},"LLeg":{"rotate":[{"value":-26.1}]},"LLeg2":{"rotate":[{"value":16.11}]},"Tail":{"rotate":[{"value":12.58}]},"Lance":{"rotate":[{"value":70.13,"curve":"stepped"},{"time":0.1667,"value":70.13},{"time":0.3333,"value":80.58}],"translate":[{"x":-49.72,"y":25.02,"curve":"stepped"},{"time":0.1667,"x":-49.72,"y":25.02},{"time":0.3333,"x":-66.11,"y":20.54}]},"Skirt2":{"rotate":[{"value":-23.05,"curve":"stepped"},{"time":0.1667,"value":-23.05},{"time":0.3333,"value":-61.1},{"time":0.5,"value":-66.96}],"translate":[{"x":11.48,"y":10.52,"curve":"stepped"},{"time":0.1667,"x":11.48,"y":10.52},{"time":0.3333,"x":25.82,"y":22.63},{"time":0.5,"x":32.51,"y":27.38}]},"Skirt":{"translate":[{"time":0.1667},{"time":0.3333,"x":-0.71,"y":10.7},{"time":0.5,"x":-1.4,"y":22.72}]},"LIK":{"translate":[{"x":-35.96,"y":-3.08}]},"RLeg2":{"rotate":[{"value":51.1}]},"root":{"translate":[{"y":0.86}]},"RIK":{"translate":[{"x":49.22,"y":-10.33,"curve":"stepped"},{"time":0.1667,"x":49.22,"y":-10.33},{"time":0.3333,"x":44.98,"y":-2.42}]}},"drawOrder":[{"offsets":[{"slot":"Lance","offset":18}]},{"time":0.5,"offsets":[{"slot":"Lance","offset":17}]}],"events":[{"time":0.5,"name":"instantiateAtk"}]},"attack_vertical/attack_vertical":{"slots":{"Braccio":{"rgba":[{"color":"858585ff"}]},"Mano":{"rgba":[{"color":"858585ff"}]}},"bones":{"root":{"translate":[{"y":0.86}]},"LArm":{"rotate":[{"value":-142.56},{"time":0.1667,"value":-62.78,"curve":"stepped"},{"time":0.3333,"value":-62.78},{"time":0.5}],"translate":[{"x":8.6,"y":11.97},{"time":0.1667,"x":-5.81,"y":-0.8,"curve":"stepped"},{"time":0.3333,"x":-5.81,"y":-0.8},{"time":0.5}],"scale":[{"x":1.175,"curve":"stepped"},{"time":0.3333,"x":1.175},{"time":0.5}]},"Body3":{"rotate":[{"value":10.94},{"time":0.1667,"value":37.21,"curve":"stepped"},{"time":0.3333,"value":37.21},{"time":0.5,"value":13.02}]},"Body2":{"rotate":[{"value":-13.83},{"time":0.1667,"value":12.44,"curve":"stepped"},{"time":0.3333,"value":12.44},{"time":0.5,"value":13.03}],"translate":[{"x":-20.08,"y":10.02,"curve":"stepped"},{"time":0.3333,"x":-20.08,"y":10.02},{"time":0.5}]},"Head":{"rotate":[{"value":19.6},{"time":0.1667,"value":-11.61,"curve":"stepped"},{"time":0.3333,"value":-11.61},{"time":0.5,"value":-8.24}],"translate":[{"x":4.72,"y":-10.99},{"time":0.1667,"x":-4.03,"y":8.44,"curve":"stepped"},{"time":0.3333,"x":-4.03,"y":8.44},{"time":0.5}]},"RArm":{"rotate":[{"value":-165.04},{"time":0.1667,"value":-33.65,"curve":"stepped"},{"time":0.3333,"value":-33.65},{"time":0.5}]},"Tail4":{"rotate":[{"value":42.38},{"time":0.1667,"value":20.79,"curve":"stepped"},{"time":0.3333,"value":20.79},{"time":0.5}]},"Body":{"rotate":[{"value":-26.86},{"time":0.1667,"value":-0.59,"curve":"stepped"},{"time":0.3333,"value":-0.59},{"time":0.5}],"translate":[{"y":-8.09},{"time":0.1667,"y":-34.95,"curve":"stepped"},{"time":0.3333,"y":-34.95},{"time":0.5,"y":-10.97}]},"RArm2":{"translate":[{"x":2.85,"y":0.25,"curve":"stepped"},{"time":0.3333,"x":2.85,"y":0.25},{"time":0.5}]},"Tail2":{"rotate":[{"value":54.96},{"time":0.1667,"value":5.22,"curve":"stepped"},{"time":0.3333,"value":5.22},{"time":0.5,"value":12.58}]},"Tail3":{"rotate":[{"value":54.96},{"time":0.1667,"value":33.37,"curve":"stepped"},{"time":0.3333,"value":33.37},{"time":0.5,"value":12.58}]},"RLeg":{"rotate":[{"value":49.85,"curve":"stepped"},{"time":0.3333,"value":49.85},{"time":0.5,"value":-18.07}]},"LLeg":{"rotate":[{"value":8.87,"curve":"stepped"},{"time":0.3333,"value":8.87},{"time":0.5,"value":-26.1}]},"LLeg2":{"rotate":[{"value":-2.6,"curve":"stepped"},{"time":0.3333,"value":-2.6},{"time":0.5,"value":16.11}]},"Tail":{"rotate":[{"value":54.96},{"time":0.1667,"value":5.22,"curve":"stepped"},{"time":0.3333,"value":5.22},{"time":0.5,"value":12.58}]},"Lance":{"rotate":[{"value":80.58},{"time":0.1,"value":102.57},{"time":0.1667,"value":81.78},{"time":0.3333,"value":82.33},{"time":0.5,"value":70.13}],"translate":[{"x":15.22,"y":-16.43},{"time":0.1667,"x":8.9,"y":-26.03},{"time":0.3333,"x":11.07,"y":-22.63},{"time":0.5,"x":-49.72,"y":25.02}]},"Skirt2":{"rotate":[{},{"time":0.1667,"value":-71.52,"curve":"stepped"},{"time":0.3333,"value":-71.52},{"time":0.5,"value":-15.28}],"translate":[{},{"time":0.1667,"x":30.05,"y":29.16,"curve":"stepped"},{"time":0.3333,"x":30.05,"y":29.16},{"time":0.5,"x":9.57,"y":8.77}]},"Skirt":{"translate":[{"x":4.73,"y":-10.21},{"time":0.1667,"x":-5.98,"y":13.87,"curve":"stepped"},{"time":0.3333,"x":-5.98,"y":13.87},{"time":0.5}]},"LIK":{"translate":[{"x":-35.96,"y":-3.08}]},"RLeg2":{"rotate":[{"value":10.79,"curve":"stepped"},{"time":0.3333,"value":10.79},{"time":0.5,"value":51.1}]},"RIK":{"translate":[{"x":44.98,"y":-2.42},{"time":0.1667,"x":50.17,"y":-1.54,"curve":"stepped"},{"time":0.3333,"x":50.17,"y":-1.54},{"time":0.5,"x":49.22,"y":-10.33}]}},"drawOrder":[{"time":0.1,"offsets":[{"slot":"Lance","offset":3}]}],"events":[{"time":0.4833,"name":"endAttackPhase"}]},"attack_vertical/attack_vertical_loop":{"slots":{"Braccio":{"rgba":[{"color":"858585ff"}]},"Mano":{"rgba":[{"color":"858585ff"}]}},"bones":{"LArm":{"rotate":[{"value":-142.56},{"time":0.3333,"value":-138.56},{"time":0.6667,"value":-142.56}],"translate":[{"x":8.6,"y":11.97}],"scale":[{"x":1.175}]},"Body3":{"rotate":[{"value":10.94},{"time":0.3333,"value":14.93},{"time":0.6667,"value":10.94}]},"Body2":{"rotate":[{"value":-13.83},{"time":0.3333,"value":-9.83},{"time":0.6667,"value":-13.83}],"translate":[{"x":-20.08,"y":10.02}]},"Head":{"rotate":[{"value":19.6},{"time":0.3333,"value":23.6},{"time":0.6667,"value":19.6}],"translate":[{"x":4.72,"y":-10.99}]},"Nose":{"rotate":[{},{"time":0.3333,"value":4},{"time":0.6667}]},"RArm":{"rotate":[{"value":-165.04},{"time":0.3333,"value":-161.04},{"time":0.6667,"value":-165.04}]},"Tail4":{"rotate":[{"value":42.38}]},"Body":{"rotate":[{"value":-26.86},{"time":0.3333,"value":-22.86},{"time":0.6667,"value":-26.86}],"translate":[{"y":-8.09}]},"Eye2":{"rotate":[{},{"time":0.3333,"value":4},{"time":0.6667}]},"LArm2":{"rotate":[{},{"time":0.3333,"value":4},{"time":0.6667}]},"RArm2":{"translate":[{"x":2.85,"y":0.25}]},"Tail2":{"rotate":[{"value":54.96}]},"Tail3":{"rotate":[{"value":54.96}]},"RLeg":{"rotate":[{"value":49.85}]},"LLeg":{"rotate":[{"value":8.87}]},"LLeg2":{"rotate":[{"value":-2.6}]},"Tail":{"rotate":[{"value":54.96},{"time":0.3333,"value":58.96},{"time":0.6667,"value":54.96}]},"Lance":{"rotate":[{"value":80.58}],"translate":[{"x":11.07,"y":-22.63}]},"Skirt2":{"rotate":[{},{"time":0.3333,"value":4},{"time":0.6667}]},"Skirt":{"translate":[{"x":4.73,"y":-10.21}]},"LIK":{"translate":[{"x":-35.96,"y":-3.08}]},"RLeg2":{"rotate":[{"value":10.79}]},"root":{"translate":[{"y":0.86}]},"RIK":{"translate":[{"x":44.98,"y":-2.42}]},"Beard":{"rotate":[{"time":0.3333,"value":4}]}},"events":[{"name":"activeAtkBaloon"}]},"attack_vertical/attack_vertical_pre":{"slots":{"Braccio":{"rgba":[{"color":"858585ff"}]},"Mano":{"rgba":[{"color":"858585ff"}]}},"bones":{"LArm":{"rotate":[{"time":0.1667},{"time":0.3333,"value":-18.92},{"time":0.5,"value":-142.56}],"translate":[{"time":0.3333},{"time":0.5,"x":8.6,"y":11.97}],"scale":[{"time":0.3333},{"time":0.5,"x":1.175}]},"Body3":{"rotate":[{"value":13.02,"curve":"stepped"},{"time":0.1667,"value":13.02},{"time":0.3333,"value":37.79},{"time":0.5,"value":10.94}]},"Body2":{"rotate":[{"value":13.03,"curve":"stepped"},{"time":0.3333,"value":13.03},{"time":0.5,"value":-13.83}],"translate":[{"time":0.1667},{"time":0.3333,"x":-20.08,"y":10.02}]},"Head":{"rotate":[{"value":-8.24,"curve":"stepped"},{"time":0.3333,"value":-8.24},{"time":0.5,"value":19.6}],"translate":[{"time":0.3333},{"time":0.5,"x":4.72,"y":-10.99}]},"RArm":{"rotate":[{"time":0.1667},{"time":0.3333,"value":-23.62},{"time":0.5,"value":-165.04}]},"Tail4":{"rotate":[{"time":0.3333},{"time":0.5,"value":42.38}]},"Body":{"rotate":[{"time":0.3333},{"time":0.5,"value":-26.86}],"translate":[{"y":-10.97,"curve":"stepped"},{"time":0.1667,"y":-10.97},{"time":0.3333,"y":-20.67},{"time":0.5,"y":-8.09}]},"RArm2":{"translate":[{"time":0.1667},{"time":0.3333,"x":2.85,"y":0.25}]},"Tail2":{"rotate":[{"value":12.58,"curve":"stepped"},{"time":0.3333,"value":12.58},{"time":0.5,"value":54.96}]},"Tail3":{"rotate":[{"value":12.58,"curve":"stepped"},{"time":0.3333,"value":12.58},{"time":0.5,"value":54.96}]},"RLeg":{"rotate":[{"value":-18.07,"curve":"stepped"},{"time":0.3333,"value":-18.07},{"time":0.5,"value":49.85}]},"LLeg":{"rotate":[{"value":-26.1,"curve":"stepped"},{"time":0.3333,"value":-26.1},{"time":0.5,"value":8.87}]},"LLeg2":{"rotate":[{"value":16.11,"curve":"stepped"},{"time":0.3333,"value":16.11},{"time":0.5,"value":-2.6}]},"Tail":{"rotate":[{"value":12.58,"curve":"stepped"},{"time":0.3333,"value":12.58},{"time":0.5,"value":54.96}]},"Lance":{"rotate":[{"value":70.13,"curve":"stepped"},{"time":0.1667,"value":70.13},{"time":0.3333,"value":80.58}],"translate":[{"x":-49.72,"y":25.02,"curve":"stepped"},{"time":0.1667,"x":-49.72,"y":25.02},{"time":0.3333,"x":-66.11,"y":20.54},{"time":0.5,"x":11.07,"y":-22.63}]},"Skirt2":{"rotate":[{"value":-19.14,"curve":"stepped"},{"time":0.1667,"value":-19.14},{"time":0.3333,"value":-51.75},{"time":0.5}],"translate":[{"x":8.32,"y":10.59,"curve":"stepped"},{"time":0.1667,"x":8.32,"y":10.59},{"time":0.3333,"x":24.53,"y":22.63},{"time":0.5}]},"Skirt":{"translate":[{"time":0.1667},{"time":0.3333,"x":-3.02,"y":15.17},{"time":0.5,"x":4.73,"y":-10.21}]},"LIK":{"translate":[{"x":-35.96,"y":-3.08}]},"RLeg2":{"rotate":[{"value":51.1,"curve":"stepped"},{"time":0.3333,"value":51.1},{"time":0.5,"value":10.79}]},"root":{"translate":[{"y":0.86}]},"RIK":{"translate":[{"x":49.22,"y":-10.33,"curve":"stepped"},{"time":0.1667,"x":49.22,"y":-10.33},{"time":0.3333,"x":44.98,"y":-2.42}]}},"drawOrder":[{"offsets":[{"slot":"Lance","offset":18}]}],"events":[{"time":0.5,"name":"instantiateAtk"}]},"scene/hungry":{"bones":{"LArm":{"rotate":[{"value":-31.41},{"time":0.5,"value":-24.43},{"time":1,"value":-31.41}],"translate":[{"x":-0.71,"y":-0.09}]},"LArm2":{"rotate":[{"value":-47.65},{"time":0.5,"value":-71.59},{"time":1,"value":-47.65}],"translate":[{"x":8.64,"y":3.48}]},"Tail2":{"rotate":[{"value":31.02},{"time":0.5,"value":12.17},{"time":1,"value":31.02}]},"Tail3":{"rotate":[{"value":66.15},{"time":0.5,"value":47.3},{"time":1,"value":66.15}]},"Tail4":{"rotate":[{"value":31.02},{"time":0.5,"value":12.17},{"time":1,"value":31.02}]},"Head":{"rotate":[{"value":28.04},{"time":0.5,"value":32.52},{"time":1,"value":28.04}]},"Body2":{"rotate":[{"value":23.49}]},"RArm":{"rotate":[{"value":-26.22}]},"Body":{"translate":[{"x":1.1,"y":-6.49},{"time":0.5,"x":0.33,"y":-1.97},{"time":1,"x":1.1,"y":-6.49}]},"root":{"translate":[{"x":0.71}]},"RLeg":{"rotate":[{"value":-14.35},{"time":0.5,"value":-7.24},{"time":1,"value":-14.35}]},"RLeg2":{"rotate":[{"value":38.26},{"time":0.5,"value":19.44},{"time":1,"value":38.26}]},"LLeg":{"rotate":[{"value":-14.5},{"time":0.5,"value":-7.51},{"time":1,"value":-14.5}]},"LLeg2":{"rotate":[{"value":40.07},{"time":0.5,"value":20.88},{"time":1,"value":40.07}]},"Tail":{"rotate":[{},{"time":0.5,"value":-18.85},{"time":1}]}}},"scene/sitdown":{"slots":{"Braccio":{"rgba":[{"color":"858585ff"}]},"Lance":{"rgba":[{"color":"858585ff"}]},"Mano":{"rgba":[{"color":"858585ff"}]}},"bones":{"Body":{"translate":[{"x":30.45,"y":-94.04}]},"LIK":{"translate":[{"x":-34.44,"y":0.5}]},"RIK":{"translate":[{"x":-44,"y":-0.87}]},"Skirt2":{"translate":[{"x":38.74,"y":1.53}]},"Skirt":{"translate":[{"x":9.21,"y":0.9}]},"Tail2":{"rotate":[{"value":46.18},{"time":0.5,"value":56.83},{"time":1,"value":46.18}]},"Tail3":{"rotate":[{"value":46.18},{"time":0.5,"value":56.83},{"time":1,"value":46.18}]},"Tail4":{"rotate":[{"value":46.18},{"time":0.5,"value":56.83},{"time":1,"value":46.18}]},"Body2":{"rotate":[{"value":29.44},{"time":0.5,"value":25.89},{"time":1,"value":29.44}]},"Body3":{"rotate":[{"value":14.81}]},"RArm":{"rotate":[{"value":-42.43},{"time":0.5,"value":-39.71},{"time":1,"value":-42.43}]},"Lance":{"rotate":[{"value":-8.22}],"translate":[{"x":-36.13,"y":-57.34}]},"RArm2":{"rotate":[{"value":-31.52}]},"LArm":{"rotate":[{"value":-63.68}],"translate":[{"x":-8.21,"y":-0.34}]},"Head":{"rotate":[{},{"time":0.5,"value":-8.53},{"time":1}]},"RLeg":{"rotate":[{"value":-110.16}]},"RLeg2":{"rotate":[{"value":90.07}]},"LLeg":{"rotate":[{"value":-112.29}]},"LLeg2":{"rotate":[{"value":105.54}]}}},"scene/standup":{"slots":{"Braccio":{"rgba":[{"color":"858585ff"}]},"Lance":{"rgba":[{"color":"858585ff"}]},"Mano":{"rgba":[{"color":"858585ff"}]}},"bones":{"Body":{"translate":[{"x":30.45,"y":-94.04},{"time":0.5,"x":12.96,"y":-41.76},{"time":1,"y":-10.97}]},"LIK":{"translate":[{"x":-34.44,"y":0.5},{"time":1,"x":-35.96,"y":-3.08}]},"RIK":{"translate":[{"x":-44,"y":-0.87},{"time":0.5,"x":36.92,"y":0.12},{"time":1,"x":49.22,"y":-10.33}]},"Skirt2":{"translate":[{"x":38.74,"y":1.53},{"time":1}]},"Skirt":{"translate":[{"x":9.21,"y":0.9},{"time":1}]},"Tail2":{"rotate":[{"value":46.18},{"time":1,"value":12.58}]},"Tail3":{"rotate":[{"value":46.18},{"time":1,"value":12.58}]},"Tail4":{"rotate":[{"value":46.18},{"time":1}]},"Body2":{"rotate":[{"value":29.44},{"time":0.5,"value":50.2},{"time":1,"value":13.03}]},"Body3":{"rotate":[{"value":14.81},{"time":1,"value":13.02}]},"RArm":{"rotate":[{"value":-42.43},{"time":1}],"translate":[{},{"time":0.5,"x":13.37,"y":-12.39},{"time":1}]},"Lance":{"rotate":[{"value":-8.22},{"time":1,"value":70.13}],"translate":[{"x":-36.13,"y":-57.34},{"time":0.5,"x":-5.31,"y":-20.74},{"time":1,"x":-49.72,"y":25.02}]},"RArm2":{"rotate":[{"value":-31.52},{"time":1}]},"LArm":{"rotate":[{"value":-63.68},{"time":0.5,"value":-80.82},{"time":1}],"translate":[{"x":-8.21,"y":-0.34},{"time":1}]},"root":{"translate":[{},{"time":1,"y":0.86}]},"Head":{"rotate":[{},{"time":0.5,"value":22.43},{"time":1,"value":-8.24}]},"RLeg":{"rotate":[{"value":-110.16},{"time":1,"value":-18.07}]},"RLeg2":{"rotate":[{"value":90.07},{"time":1,"value":51.1}]},"LLeg":{"rotate":[{"value":-112.29},{"time":1,"value":-26.1}]},"LLeg2":{"rotate":[{"value":105.54},{"time":1,"value":16.11}]},"Tail":{"rotate":[{},{"time":1,"value":12.58}]}},"drawOrder":[{"time":1,"offsets":[{"slot":"Lance","offset":17}]}]},"scene/surprise":{"slots":{"Braccio":{"rgba":[{"color":"858585ff"}]},"Mano":{"rgba":[{"color":"858585ff"}]}},"bones":{"Body":{"translate":[{"y":-10.97},{"time":0.0833,"x":27.33,"y":22.65},{"time":0.6667,"y":-10.97}]},"LIK":{"translate":[{"x":-35.96,"y":-3.08}]},"RIK":{"translate":[{"x":49.22,"y":-10.33}]},"Tail2":{"rotate":[{"value":12.58},{"time":0.0833,"value":47.66},{"time":0.6667,"value":12.58}]},"Tail3":{"rotate":[{"value":12.58},{"time":0.0833,"value":47.66},{"time":0.6667,"value":12.58}]},"Tail4":{"rotate":[{},{"time":0.0833,"value":35.09},{"time":0.6667}]},"Body2":{"rotate":[{"value":13.03},{"time":0.0833,"value":-0.5},{"time":0.6667,"value":13.03}]},"Body3":{"rotate":[{"value":13.02}]},"Lance":{"rotate":[{"value":70.13}],"translate":[{"x":-49.72,"y":25.02}]},"root":{"translate":[{"y":0.86}]},"Head":{"rotate":[{"value":-8.24},{"time":0.0833,"value":6.89},{"time":0.6667,"value":-8.24}]},"Ears":{"rotate":[{},{"time":0.0833,"value":-33.17},{"time":0.6667}]},"Ears2":{"rotate":[{},{"time":0.0833,"value":33.32},{"time":0.6667}]},"Eye":{"rotate":[{},{"time":0.0833,"value":-38.58},{"time":0.6667}]},"Eye2":{"rotate":[{},{"time":0.0833,"value":39.76},{"time":0.6667}]},"RLeg":{"rotate":[{"value":-18.07}]},"RLeg2":{"rotate":[{"value":51.1}]},"LLeg":{"rotate":[{"value":-26.1}]},"LLeg2":{"rotate":[{"value":16.11}]},"Tail":{"rotate":[{"value":12.58},{"time":0.0833,"value":47.66},{"time":0.6667,"value":12.58}]}},"drawOrder":[{"offsets":[{"slot":"Lance","offset":17}]}]}}}